{
  "updated_at": "20/04/2026 18:12:50",
  "summary": {
    "total": 360,
    "finalizados": 300,
    "agendados": 60,
    "ligas": 20
  },
  "jogos": [
    {
      "liga": "FC26 R61(CHAMPIONS LEAGUE)19.04.2026",
      "p1": "Bayern M. (Dexter)",
      "p2": "Real Madrid (Kai)",
      "placar": "2-4",
      "status": "Finalizado"
    },
    {
      "liga": "FC26 R61(CHAMPIONS LEAGUE)19.04.2026",
      "p1": "Liverpool (Conde)",
      "p2": "Atletico Madrid (Odin)",
      "placar": "0-4",
      "status": "Finalizado"
    },
    {
      "liga": "FC26 R61(CHAMPIONS LEAGUE)19.04.2026",
      "p1": "Bayern M. (Dexter)",
      "p2": "Barcelona (Eduardo)",
      "placar": "0-1",
      "status": "Finalizado"
    },
    {
      "liga": "FC26 R61(CHAMPIONS LEAGUE)19.04.2026",
      "p1": "Real Madrid (Kai)",
      "p2": "Atletico Madrid (Odin)",
      "placar": "2-4",
      "status": "Finalizado"
    },
    {
      "liga": "FC26 R61(CHAMPIONS LEAGUE)19.04.2026",
      "p1": "Barcelona (Eduardo)",
      "p2": "Atletico Madrid (Odin)",
      "placar": "1-0",
      "status": "Finalizado"
    },
    {
      "liga": "FC26 R61(CHAMPIONS LEAGUE)19.04.2026",
      "p1": "Real Madrid (Kai)",
      "p2": "Liverpool (Conde)",
      "placar": "2-4",
      "status": "Finalizado"
    },
    {
      "liga": "FC26 R61(CHAMPIONS LEAGUE)19.04.2026",
      "p1": "Barcelona (Eduardo)",
      "p2": "Real Madrid (Kai)",
      "placar": "2-2",
      "status": "Finalizado"
    },
    {
      "liga": "FC26 R61(CHAMPIONS LEAGUE)19.04.2026",
      "p1": "Bayern M. (Dexter)",
      "p2": "Liverpool (Conde)",
      "placar": "6-1",
      "status": "Finalizado"
    },
    {
      "liga": "FC26 R61(CHAMPIONS LEAGUE)19.04.2026",
      "p1": "Atletico Madrid (Odin)",
      "p2": "Bayern M. (Dexter)",
      "placar": "1-2",
      "status": "Finalizado"
    },
    {
      "liga": "FC26 R61(CHAMPIONS LEAGUE)19.04.2026",
      "p1": "Barcelona (Eduardo)",
      "p2": "Liverpool (Conde)",
      "placar": "4-1",
      "status": "Finalizado"
    },
    {
      "liga": "FC26 R61(CHAMPIONS LEAGUE)19.04.2026",
      "p1": "Atletico Madrid (Odin)",
      "p2": "Liverpool (Conde)",
      "placar": "6-2",
      "status": "Finalizado"
    },
    {
      "liga": "FC26 R61(CHAMPIONS LEAGUE)19.04.2026",
      "p1": "Real Madrid (Kai)",
      "p2": "Bayern M. (Dexter)",
      "placar": "2-2",
      "status": "Finalizado"
    },
    {
      "liga": "FC26 R62(INTERNATIONAL)19.04.2026",
      "p1": "France (George)",
      "p2": "Italy (Eric)",
      "placar": "2-1",
      "status": "Finalizado"
    },
    {
      "liga": "FC26 R62(INTERNATIONAL)19.04.2026",
      "p1": "Morocco (Haidan)",
      "p2": "Ghana (Splinter)",
      "placar": "6-3",
      "status": "Finalizado"
    },
    {
      "liga": "FC26 R62(INTERNATIONAL)19.04.2026",
      "p1": "France (George)",
      "p2": "Denmark (Felix)",
      "placar": "2-2",
      "status": "Finalizado"
    },
    {
      "liga": "FC26 R62(INTERNATIONAL)19.04.2026",
      "p1": "Morocco (Haidan)",
      "p2": "Italy (Eric)",
      "placar": "4-6",
      "status": "Finalizado"
    },
    {
      "liga": "FC26 R62(INTERNATIONAL)19.04.2026",
      "p1": "Denmark (Felix)",
      "p2": "Italy (Eric)",
      "placar": "4-5",
      "status": "Finalizado"
    },
    {
      "liga": "FC26 R62(INTERNATIONAL)19.04.2026",
      "p1": "France (George)",
      "p2": "Ghana (Splinter)",
      "placar": "2-3",
      "status": "Finalizado"
    },
    {
      "liga": "FC26 R62(INTERNATIONAL)19.04.2026",
      "p1": "Denmark (Felix)",
      "p2": "Morocco (Haidan)",
      "placar": "3-4",
      "status": "Finalizado"
    },
    {
      "liga": "FC26 R62(INTERNATIONAL)19.04.2026",
      "p1": "Ghana (Splinter)",
      "p2": "Italy (Eric)",
      "placar": "1-2",
      "status": "Finalizado"
    },
    {
      "liga": "FC26 R62(INTERNATIONAL)19.04.2026",
      "p1": "France (George)",
      "p2": "Morocco (Haidan)",
      "placar": "3-6",
      "status": "Finalizado"
    },
    {
      "liga": "FC26 R62(INTERNATIONAL)19.04.2026",
      "p1": "Ghana (Splinter)",
      "p2": "Denmark (Felix)",
      "placar": "1-3",
      "status": "Finalizado"
    },
    {
      "liga": "FC26 R62(INTERNATIONAL)19.04.2026",
      "p1": "Ghana (Splinter)",
      "p2": "Morocco (Haidan)",
      "placar": "5-5",
      "status": "Finalizado"
    },
    {
      "liga": "FC26 R62(INTERNATIONAL)19.04.2026",
      "p1": "Italy (Eric)",
      "p2": "France (George)",
      "placar": "5-4",
      "status": "Finalizado"
    },
    {
      "liga": "FC26 R62(INTERNATIONAL)19.04.2026",
      "p1": "Denmark (Felix)",
      "p2": "France (George)",
      "placar": "1-1",
      "status": "Finalizado"
    },
    {
      "liga": "FC26 R62(INTERNATIONAL)19.04.2026",
      "p1": "Italy (Eric)",
      "p2": "Morocco (Haidan)",
      "placar": "6-5",
      "status": "Finalizado"
    },
    {
      "liga": "FC26 R63(PREMIER LEAGUE)20.04.2026",
      "p1": "Aston Villa (Eduardo)",
      "p2": "Manchester City (Dexter)",
      "placar": "3-1",
      "status": "Finalizado"
    },
    {
      "liga": "FC26 R63(PREMIER LEAGUE)20.04.2026",
      "p1": "West Ham United (Odin)",
      "p2": "Liverpool (Kai)",
      "placar": "5-2",
      "status": "Finalizado"
    },
    {
      "liga": "FC26 R63(PREMIER LEAGUE)20.04.2026",
      "p1": "Arsenal (Conde)",
      "p2": "Liverpool (Kai)",
      "placar": "2-2",
      "status": "Finalizado"
    },
    {
      "liga": "FC26 R63(PREMIER LEAGUE)20.04.2026",
      "p1": "West Ham United (Odin)",
      "p2": "Aston Villa (Eduardo)",
      "placar": "1-3",
      "status": "Finalizado"
    },
    {
      "liga": "FC26 R63(PREMIER LEAGUE)20.04.2026",
      "p1": "Arsenal (Conde)",
      "p2": "Manchester City (Dexter)",
      "placar": "3-2",
      "status": "Finalizado"
    },
    {
      "liga": "FC26 R63(PREMIER LEAGUE)20.04.2026",
      "p1": "Liverpool (Kai)",
      "p2": "Aston Villa (Eduardo)",
      "placar": "3-0",
      "status": "Finalizado"
    },
    {
      "liga": "FC26 R63(PREMIER LEAGUE)20.04.2026",
      "p1": "Arsenal (Conde)",
      "p2": "Aston Villa (Eduardo)",
      "placar": "2-0",
      "status": "Finalizado"
    },
    {
      "liga": "FC26 R63(PREMIER LEAGUE)20.04.2026",
      "p1": "Manchester City (Dexter)",
      "p2": "West Ham United (Odin)",
      "placar": "6-3",
      "status": "Finalizado"
    },
    {
      "liga": "FC26 R63(PREMIER LEAGUE)20.04.2026",
      "p1": "Arsenal (Conde)",
      "p2": "West Ham United (Odin)",
      "placar": "5-3",
      "status": "Finalizado"
    },
    {
      "liga": "FC26 R63(PREMIER LEAGUE)20.04.2026",
      "p1": "Manchester City (Dexter)",
      "p2": "Liverpool (Kai)",
      "placar": "2-2",
      "status": "Finalizado"
    },
    {
      "liga": "FC26 R63(PREMIER LEAGUE)20.04.2026",
      "p1": "Liverpool (Kai)",
      "p2": "West Ham United (Odin)",
      "placar": "2-5",
      "status": "Finalizado"
    },
    {
      "liga": "FC26 R63(PREMIER LEAGUE)20.04.2026",
      "p1": "Manchester City (Dexter)",
      "p2": "Aston Villa (Eduardo)",
      "placar": "1-1",
      "status": "Finalizado"
    },
    {
      "liga": "FC26 R63(PREMIER LEAGUE)20.04.2026",
      "p1": "Aston Villa (Eduardo)",
      "p2": "West Ham United (Odin)",
      "placar": "3-1",
      "status": "Finalizado"
    },
    {
      "liga": "FC26 R63(PREMIER LEAGUE)20.04.2026",
      "p1": "Liverpool (Kai)",
      "p2": "Arsenal (Conde)",
      "placar": "4-4",
      "status": "Finalizado"
    },
    {
      "liga": "FC26 R63(PREMIER LEAGUE)20.04.2026",
      "p1": "Aston Villa (Eduardo)",
      "p2": "Liverpool (Kai)",
      "placar": "3-1",
      "status": "Finalizado"
    },
    {
      "liga": "FC26 R63(PREMIER LEAGUE)20.04.2026",
      "p1": "Manchester City (Dexter)",
      "p2": "Arsenal (Conde)",
      "placar": "3-1",
      "status": "Finalizado"
    },
    {
      "liga": "FC26 R63(PREMIER LEAGUE)20.04.2026",
      "p1": "Aston Villa (Eduardo)",
      "p2": "Arsenal (Conde)",
      "placar": "4-2",
      "status": "Finalizado"
    },
    {
      "liga": "FC26 R63(PREMIER LEAGUE)20.04.2026",
      "p1": "West Ham United (Odin)",
      "p2": "Manchester City (Dexter)",
      "placar": "3-2",
      "status": "Finalizado"
    },
    {
      "liga": "FC26 R63(PREMIER LEAGUE)20.04.2026",
      "p1": "Liverpool (Kai)",
      "p2": "Manchester City (Dexter)",
      "placar": "3-5",
      "status": "Finalizado"
    },
    {
      "liga": "FC26 R63(PREMIER LEAGUE)20.04.2026",
      "p1": "West Ham United (Odin)",
      "p2": "Arsenal (Conde)",
      "placar": "7-5",
      "status": "Finalizado"
    },
    {
      "liga": "FC26 R64(SERIA A)20.04.2026",
      "p1": "Juventus (Eric)",
      "p2": "Atalanta (Felix)",
      "placar": "8-3",
      "status": "Finalizado"
    },
    {
      "liga": "FC26 R64(SERIA A)20.04.2026",
      "p1": "Roma (Splinter)",
      "p2": "Milan (George)",
      "placar": "0-2",
      "status": "Finalizado"
    },
    {
      "liga": "FC26 R64(SERIA A)20.04.2026",
      "p1": "Fiorentina (Haidan)",
      "p2": "Atalanta (Felix)",
      "placar": "7-3",
      "status": "Finalizado"
    },
    {
      "liga": "FC26 R64(SERIA A)20.04.2026",
      "p1": "Juventus (Eric)",
      "p2": "Roma (Splinter)",
      "placar": "4-2",
      "status": "Finalizado"
    },
    {
      "liga": "FC26 R64(SERIA A)20.04.2026",
      "p1": "Atalanta (Felix)",
      "p2": "Roma (Splinter)",
      "placar": "3-5",
      "status": "Finalizado"
    },
    {
      "liga": "FC26 R64(SERIA A)20.04.2026",
      "p1": "Fiorentina (Haidan)",
      "p2": "Milan (George)",
      "placar": "3-3",
      "status": "Finalizado"
    },
    {
      "liga": "FC26 R64(SERIA A)20.04.2026",
      "p1": "Fiorentina (Haidan)",
      "p2": "Roma (Splinter)",
      "placar": "5-5",
      "status": "Finalizado"
    },
    {
      "liga": "FC26 R64(SERIA A)20.04.2026",
      "p1": "Milan (George)",
      "p2": "Juventus (Eric)",
      "placar": "2-4",
      "status": "Finalizado"
    },
    {
      "liga": "FC26 R64(SERIA A)20.04.2026",
      "p1": "Fiorentina (Haidan)",
      "p2": "Juventus (Eric)",
      "placar": "5-7",
      "status": "Finalizado"
    },
    {
      "liga": "FC26 R64(SERIA A)20.04.2026",
      "p1": "Milan (George)",
      "p2": "Atalanta (Felix)",
      "placar": "0-1",
      "status": "Finalizado"
    },
    {
      "liga": "FC26 R64(SERIA A)20.04.2026",
      "p1": "Atalanta (Felix)",
      "p2": "Juventus (Eric)",
      "placar": "8-4",
      "status": "Finalizado"
    },
    {
      "liga": "FC26 R64(SERIA A)20.04.2026",
      "p1": "Milan (George)",
      "p2": "Roma (Splinter)",
      "placar": "0-1",
      "status": "Finalizado"
    },
    {
      "liga": "FC26 R64(SERIA A)20.04.2026",
      "p1": "Atalanta (Felix)",
      "p2": "Fiorentina (Haidan)",
      "placar": "7-4",
      "status": "Finalizado"
    },
    {
      "liga": "FC26 R64(SERIA A)20.04.2026",
      "p1": "Roma (Splinter)",
      "p2": "Juventus (Eric)",
      "placar": "4-5",
      "status": "Finalizado"
    },
    {
      "liga": "FC26 R64(SERIA A)20.04.2026",
      "p1": "Milan (George)",
      "p2": "Fiorentina (Haidan)",
      "placar": "4-0",
      "status": "Finalizado"
    },
    {
      "liga": "FC26 R64(SERIA A)20.04.2026",
      "p1": "Roma (Splinter)",
      "p2": "Atalanta (Felix)",
      "placar": "4-2",
      "status": "Finalizado"
    },
    {
      "liga": "FC26 R64(SERIA A)20.04.2026",
      "p1": "Juventus (Eric)",
      "p2": "Milan (George)",
      "placar": "3-4",
      "status": "Finalizado"
    },
    {
      "liga": "FC26 R64(SERIA A)20.04.2026",
      "p1": "Roma (Splinter)",
      "p2": "Fiorentina (Haidan)",
      "placar": "6-6",
      "status": "Finalizado"
    },
    {
      "liga": "FC26 R64(SERIA A)20.04.2026",
      "p1": "Atalanta (Felix)",
      "p2": "Milan (George)",
      "placar": "3-3",
      "status": "Finalizado"
    },
    {
      "liga": "FC26 R64(SERIA A)20.04.2026",
      "p1": "Juventus (Eric)",
      "p2": "Fiorentina (Haidan)",
      "placar": "6-3",
      "status": "Finalizado"
    },
    {
      "liga": "FC26 R65(COPA LIBERTADORES)20.04.2026",
      "p1": "San Lorenzo (Eduardo)",
      "p2": "Penarol (Dexter)",
      "placar": "4-3",
      "status": "Finalizado"
    },
    {
      "liga": "FC26 R65(COPA LIBERTADORES)20.04.2026",
      "p1": "Sao Paulo (Odin)",
      "p2": "River Plate (Kai)",
      "placar": "5-1",
      "status": "Finalizado"
    },
    {
      "liga": "FC26 R65(COPA LIBERTADORES)20.04.2026",
      "p1": "Bolivar (Conde)",
      "p2": "River Plate (Kai)",
      "placar": "3-2",
      "status": "Finalizado"
    },
    {
      "liga": "FC26 R65(COPA LIBERTADORES)20.04.2026",
      "p1": "Sao Paulo (Odin)",
      "p2": "San Lorenzo (Eduardo)",
      "placar": "0-0",
      "status": "Finalizado"
    },
    {
      "liga": "FC26 R65(COPA LIBERTADORES)20.04.2026",
      "p1": "Bolivar (Conde)",
      "p2": "Penarol (Dexter)",
      "placar": "3-8",
      "status": "Finalizado"
    },
    {
      "liga": "FC26 R65(COPA LIBERTADORES)20.04.2026",
      "p1": "River Plate (Kai)",
      "p2": "San Lorenzo (Eduardo)",
      "placar": "2-4",
      "status": "Finalizado"
    },
    {
      "liga": "FC26 R65(COPA LIBERTADORES)20.04.2026",
      "p1": "Bolivar (Conde)",
      "p2": "San Lorenzo (Eduardo)",
      "placar": "5-5",
      "status": "Finalizado"
    },
    {
      "liga": "FC26 R65(COPA LIBERTADORES)20.04.2026",
      "p1": "Penarol (Dexter)",
      "p2": "Sao Paulo (Odin)",
      "placar": "4-3",
      "status": "Finalizado"
    },
    {
      "liga": "FC26 R65(COPA LIBERTADORES)20.04.2026",
      "p1": "Bolivar (Conde)",
      "p2": "Sao Paulo (Odin)",
      "placar": "3-3",
      "status": "Finalizado"
    },
    {
      "liga": "FC26 R65(COPA LIBERTADORES)20.04.2026",
      "p1": "Penarol (Dexter)",
      "p2": "River Plate (Kai)",
      "placar": "1-4",
      "status": "Finalizado"
    },
    {
      "liga": "FC26 R65(COPA LIBERTADORES)20.04.2026",
      "p1": "Penarol (Dexter)",
      "p2": "San Lorenzo (Eduardo)",
      "placar": "4-2",
      "status": "Finalizado"
    },
    {
      "liga": "FC26 R65(COPA LIBERTADORES)20.04.2026",
      "p1": "River Plate (Kai)",
      "p2": "Sao Paulo (Odin)",
      "placar": "1-3",
      "status": "Finalizado"
    },
    {
      "liga": "FC26 R65(COPA LIBERTADORES)20.04.2026",
      "p1": "River Plate (Kai)",
      "p2": "Bolivar (Conde)",
      "placar": "1-3",
      "status": "Finalizado"
    },
    {
      "liga": "FC26 R65(COPA LIBERTADORES)20.04.2026",
      "p1": "San Lorenzo (Eduardo)",
      "p2": "Sao Paulo (Odin)",
      "placar": "1-2",
      "status": "Finalizado"
    },
    {
      "liga": "FC26 R65(COPA LIBERTADORES)20.04.2026",
      "p1": "Penarol (Dexter)",
      "p2": "Bolivar (Conde)",
      "placar": "2-2",
      "status": "Finalizado"
    },
    {
      "liga": "FC26 R65(COPA LIBERTADORES)20.04.2026",
      "p1": "San Lorenzo (Eduardo)",
      "p2": "River Plate (Kai)",
      "placar": "0-2",
      "status": "Finalizado"
    },
    {
      "liga": "FC26 R65(COPA LIBERTADORES)20.04.2026",
      "p1": "San Lorenzo (Eduardo)",
      "p2": "Bolivar (Conde)",
      "placar": "3-1",
      "status": "Finalizado"
    },
    {
      "liga": "FC26 R65(COPA LIBERTADORES)20.04.2026",
      "p1": "Sao Paulo (Odin)",
      "p2": "Penarol (Dexter)",
      "placar": "3-4",
      "status": "Finalizado"
    },
    {
      "liga": "FC26 R65(COPA LIBERTADORES)20.04.2026",
      "p1": "River Plate (Kai)",
      "p2": "Penarol (Dexter)",
      "placar": "4-1",
      "status": "Finalizado"
    },
    {
      "liga": "FC26 R65(COPA LIBERTADORES)20.04.2026",
      "p1": "Sao Paulo (Odin)",
      "p2": "Bolivar (Conde)",
      "placar": "10-2",
      "status": "Finalizado"
    },
    {
      "liga": "FC26 R66(CHAMPIONS LEAGUE)20.04.2026",
      "p1": "Borussia Dortmund (Splinter)",
      "p2": "Bayern M. (George)",
      "placar": "1-1",
      "status": "Finalizado"
    },
    {
      "liga": "FC26 R66(CHAMPIONS LEAGUE)20.04.2026",
      "p1": "Manchester City (Eric)",
      "p2": "PSG (Felix)",
      "placar": "3-3",
      "status": "Finalizado"
    },
    {
      "liga": "FC26 R66(CHAMPIONS LEAGUE)20.04.2026",
      "p1": "Bayer Leverkusen (Haidan)",
      "p2": "PSG (Felix)",
      "placar": "2-6",
      "status": "Finalizado"
    },
    {
      "liga": "FC26 R66(CHAMPIONS LEAGUE)20.04.2026",
      "p1": "Manchester City (Eric)",
      "p2": "Borussia Dortmund (Splinter)",
      "placar": "4-2",
      "status": "Finalizado"
    },
    {
      "liga": "FC26 R66(CHAMPIONS LEAGUE)20.04.2026",
      "p1": "Bayer Leverkusen (Haidan)",
      "p2": "Bayern M. (George)",
      "placar": "2-7",
      "status": "Finalizado"
    },
    {
      "liga": "FC26 R66(CHAMPIONS LEAGUE)20.04.2026",
      "p1": "PSG (Felix)",
      "p2": "Borussia Dortmund (Splinter)",
      "placar": "3-3",
      "status": "Finalizado"
    },
    {
      "liga": "FC26 R66(CHAMPIONS LEAGUE)20.04.2026",
      "p1": "Bayer Leverkusen (Haidan)",
      "p2": "Borussia Dortmund (Splinter)",
      "placar": "4-7",
      "status": "Finalizado"
    },
    {
      "liga": "FC26 R66(CHAMPIONS LEAGUE)20.04.2026",
      "p1": "Bayern M. (George)",
      "p2": "Manchester City (Eric)",
      "placar": "4-1",
      "status": "Finalizado"
    },
    {
      "liga": "FC26 R66(CHAMPIONS LEAGUE)20.04.2026",
      "p1": "Bayer Leverkusen (Haidan)",
      "p2": "Manchester City (Eric)",
      "placar": "3-5",
      "status": "Finalizado"
    },
    {
      "liga": "FC26 R66(CHAMPIONS LEAGUE)20.04.2026",
      "p1": "Bayern M. (George)",
      "p2": "PSG (Felix)",
      "placar": "2-1",
      "status": "Finalizado"
    },
    {
      "liga": "FC26 R66(CHAMPIONS LEAGUE)20.04.2026",
      "p1": "Bayern M. (George)",
      "p2": "Borussia Dortmund (Splinter)",
      "placar": "3-0",
      "status": "Finalizado"
    },
    {
      "liga": "FC26 R66(CHAMPIONS LEAGUE)20.04.2026",
      "p1": "PSG (Felix)",
      "p2": "Manchester City (Eric)",
      "placar": "8-6",
      "status": "Finalizado"
    },
    {
      "liga": "FC26 R66(CHAMPIONS LEAGUE)20.04.2026",
      "p1": "Borussia Dortmund (Splinter)",
      "p2": "Manchester City (Eric)",
      "placar": "3-3",
      "status": "Finalizado"
    },
    {
      "liga": "FC26 R66(CHAMPIONS LEAGUE)20.04.2026",
      "p1": "PSG (Felix)",
      "p2": "Bayer Leverkusen (Haidan)",
      "placar": "5-2",
      "status": "Finalizado"
    },
    {
      "liga": "FC26 R66(CHAMPIONS LEAGUE)20.04.2026",
      "p1": "Bayern M. (George)",
      "p2": "Bayer Leverkusen (Haidan)",
      "placar": "6-4",
      "status": "Finalizado"
    },
    {
      "liga": "FC26 R66(CHAMPIONS LEAGUE)20.04.2026",
      "p1": "Borussia Dortmund (Splinter)",
      "p2": "PSG (Felix)",
      "placar": "3-2",
      "status": "Finalizado"
    },
    {
      "liga": "FC26 R66(CHAMPIONS LEAGUE)20.04.2026",
      "p1": "Borussia Dortmund (Splinter)",
      "p2": "Bayer Leverkusen (Haidan)",
      "placar": "2-3",
      "status": "Finalizado"
    },
    {
      "liga": "FC26 R66(CHAMPIONS LEAGUE)20.04.2026",
      "p1": "Manchester City (Eric)",
      "p2": "Bayern M. (George)",
      "placar": "6-1",
      "status": "Finalizado"
    },
    {
      "liga": "FC26 R66(CHAMPIONS LEAGUE)20.04.2026",
      "p1": "Manchester City (Eric)",
      "p2": "Bayer Leverkusen (Haidan)",
      "placar": "2-4",
      "status": "Finalizado"
    },
    {
      "liga": "FC26 R66(CHAMPIONS LEAGUE)20.04.2026",
      "p1": "PSG (Felix)",
      "p2": "Bayern M. (George)",
      "placar": "1-2",
      "status": "Finalizado"
    },
    {
      "liga": "FC26 R67(PREMIER LEAGUE)20.04.2026",
      "p1": "Manchester City (Cleo)",
      "p2": "Arsenal (Leonardo)",
      "placar": "4-1",
      "status": "Finalizado"
    },
    {
      "liga": "FC26 R67(PREMIER LEAGUE)20.04.2026",
      "p1": "Tottenham (Flash)",
      "p2": "Aston Villa (Alexis)",
      "placar": "2-4",
      "status": "Finalizado"
    },
    {
      "liga": "FC26 R67(PREMIER LEAGUE)20.04.2026",
      "p1": "Chelsea (Gabriel)",
      "p2": "Arsenal (Leonardo)",
      "placar": "2-3",
      "status": "Finalizado"
    },
    {
      "liga": "FC26 R67(PREMIER LEAGUE)20.04.2026",
      "p1": "Manchester City (Cleo)",
      "p2": "Tottenham (Flash)",
      "placar": "3-5",
      "status": "Finalizado"
    },
    {
      "liga": "FC26 R67(PREMIER LEAGUE)20.04.2026",
      "p1": "Arsenal (Leonardo)",
      "p2": "Tottenham (Flash)",
      "placar": "6-8",
      "status": "Finalizado"
    },
    {
      "liga": "FC26 R67(PREMIER LEAGUE)20.04.2026",
      "p1": "Chelsea (Gabriel)",
      "p2": "Aston Villa (Alexis)",
      "placar": "3-3",
      "status": "Finalizado"
    },
    {
      "liga": "FC26 R67(PREMIER LEAGUE)20.04.2026",
      "p1": "Aston Villa (Alexis)",
      "p2": "Manchester City (Cleo)",
      "placar": "4-1",
      "status": "Finalizado"
    },
    {
      "liga": "FC26 R67(PREMIER LEAGUE)20.04.2026",
      "p1": "Chelsea (Gabriel)",
      "p2": "Tottenham (Flash)",
      "placar": "5-1",
      "status": "Finalizado"
    },
    {
      "liga": "FC26 R67(PREMIER LEAGUE)20.04.2026",
      "p1": "Aston Villa (Alexis)",
      "p2": "Arsenal (Leonardo)",
      "placar": "5-1",
      "status": "Finalizado"
    },
    {
      "liga": "FC26 R67(PREMIER LEAGUE)20.04.2026",
      "p1": "Chelsea (Gabriel)",
      "p2": "Manchester City (Cleo)",
      "placar": "4-4",
      "status": "Finalizado"
    },
    {
      "liga": "FC26 R67(PREMIER LEAGUE)20.04.2026",
      "p1": "Arsenal (Leonardo)",
      "p2": "Manchester City (Cleo)",
      "placar": "2-5",
      "status": "Finalizado"
    },
    {
      "liga": "FC26 R67(PREMIER LEAGUE)20.04.2026",
      "p1": "Aston Villa (Alexis)",
      "p2": "Tottenham (Flash)",
      "placar": "7-3",
      "status": "Finalizado"
    },
    {
      "liga": "FC26 R67(PREMIER LEAGUE)20.04.2026",
      "p1": "Arsenal (Leonardo)",
      "p2": "Chelsea (Gabriel)",
      "placar": "4-6",
      "status": "Finalizado"
    },
    {
      "liga": "FC26 R67(PREMIER LEAGUE)20.04.2026",
      "p1": "Tottenham (Flash)",
      "p2": "Manchester City (Cleo)",
      "placar": "4-2",
      "status": "Finalizado"
    },
    {
      "liga": "FC26 R67(PREMIER LEAGUE)20.04.2026",
      "p1": "Aston Villa (Alexis)",
      "p2": "Chelsea (Gabriel)",
      "placar": "3-2",
      "status": "Finalizado"
    },
    {
      "liga": "FC26 R67(PREMIER LEAGUE)20.04.2026",
      "p1": "Tottenham (Flash)",
      "p2": "Arsenal (Leonardo)",
      "placar": "4-2",
      "status": "Finalizado"
    },
    {
      "liga": "FC26 R67(PREMIER LEAGUE)20.04.2026",
      "p1": "Manchester City (Cleo)",
      "p2": "Aston Villa (Alexis)",
      "placar": "1-4",
      "status": "Finalizado"
    },
    {
      "liga": "FC26 R67(PREMIER LEAGUE)20.04.2026",
      "p1": "Tottenham (Flash)",
      "p2": "Chelsea (Gabriel)",
      "placar": "2-1",
      "status": "Finalizado"
    },
    {
      "liga": "FC26 R67(PREMIER LEAGUE)20.04.2026",
      "p1": "Arsenal (Leonardo)",
      "p2": "Aston Villa (Alexis)",
      "placar": "5-1",
      "status": "Finalizado"
    },
    {
      "liga": "FC26 R67(PREMIER LEAGUE)20.04.2026",
      "p1": "Manchester City (Cleo)",
      "p2": "Chelsea (Gabriel)",
      "placar": "2-3",
      "status": "Finalizado"
    },
    {
      "liga": "FC26 R68(CHAMPIONS LEAGUE)20.04.2026",
      "p1": "Atletico Madrid (Andrew)",
      "p2": "Barcelona (Mateo)",
      "placar": "4-2",
      "status": "Finalizado"
    },
    {
      "liga": "FC26 R68(CHAMPIONS LEAGUE)20.04.2026",
      "p1": "Liverpool (Luigi)",
      "p2": "Real Madrid (VanGogh)",
      "placar": "3-5",
      "status": "Finalizado"
    },
    {
      "liga": "FC26 R68(CHAMPIONS LEAGUE)20.04.2026",
      "p1": "Atletico Madrid (Andrew)",
      "p2": "Liverpool (Luigi)",
      "placar": "2-5",
      "status": "Finalizado"
    },
    {
      "liga": "FC26 R68(CHAMPIONS LEAGUE)20.04.2026",
      "p1": "Manchester City (MisterX)",
      "p2": "Barcelona (Mateo)",
      "placar": "3-6",
      "status": "Finalizado"
    },
    {
      "liga": "FC26 R68(CHAMPIONS LEAGUE)20.04.2026",
      "p1": "Barcelona (Mateo)",
      "p2": "Liverpool (Luigi)",
      "placar": "5-5",
      "status": "Finalizado"
    },
    {
      "liga": "FC26 R68(CHAMPIONS LEAGUE)20.04.2026",
      "p1": "Manchester City (MisterX)",
      "p2": "Real Madrid (VanGogh)",
      "placar": "4-7",
      "status": "Finalizado"
    },
    {
      "liga": "FC26 R68(CHAMPIONS LEAGUE)20.04.2026",
      "p1": "Manchester City (MisterX)",
      "p2": "Liverpool (Luigi)",
      "placar": "5-4",
      "status": "Finalizado"
    },
    {
      "liga": "FC26 R68(CHAMPIONS LEAGUE)20.04.2026",
      "p1": "Real Madrid (VanGogh)",
      "p2": "Atletico Madrid (Andrew)",
      "placar": "1-2",
      "status": "Finalizado"
    },
    {
      "liga": "FC26 R68(CHAMPIONS LEAGUE)20.04.2026",
      "p1": "Manchester City (MisterX)",
      "p2": "Atletico Madrid (Andrew)",
      "placar": "2-5",
      "status": "Finalizado"
    },
    {
      "liga": "FC26 R68(CHAMPIONS LEAGUE)20.04.2026",
      "p1": "Real Madrid (VanGogh)",
      "p2": "Barcelona (Mateo)",
      "placar": "2-3",
      "status": "Finalizado"
    },
    {
      "liga": "FC26 R68(CHAMPIONS LEAGUE)20.04.2026",
      "p1": "Barcelona (Mateo)",
      "p2": "Atletico Madrid (Andrew)",
      "placar": "4-6",
      "status": "Finalizado"
    },
    {
      "liga": "FC26 R68(CHAMPIONS LEAGUE)20.04.2026",
      "p1": "Real Madrid (VanGogh)",
      "p2": "Liverpool (Luigi)",
      "placar": "1-2",
      "status": "Finalizado"
    },
    {
      "liga": "FC26 R68(CHAMPIONS LEAGUE)20.04.2026",
      "p1": "Barcelona (Mateo)",
      "p2": "Manchester City (MisterX)",
      "placar": "7-3",
      "status": "Finalizado"
    },
    {
      "liga": "FC26 R68(CHAMPIONS LEAGUE)20.04.2026",
      "p1": "Liverpool (Luigi)",
      "p2": "Atletico Madrid (Andrew)",
      "placar": "6-2",
      "status": "Finalizado"
    },
    {
      "liga": "FC26 R68(CHAMPIONS LEAGUE)20.04.2026",
      "p1": "Liverpool (Luigi)",
      "p2": "Barcelona (Mateo)",
      "placar": "4-3",
      "status": "Finalizado"
    },
    {
      "liga": "FC26 R68(CHAMPIONS LEAGUE)20.04.2026",
      "p1": "Real Madrid (VanGogh)",
      "p2": "Manchester City (MisterX)",
      "placar": "5-3",
      "status": "Finalizado"
    },
    {
      "liga": "FC26 R68(CHAMPIONS LEAGUE)20.04.2026",
      "p1": "Atletico Madrid (Andrew)",
      "p2": "Real Madrid (VanGogh)",
      "placar": "5-2",
      "status": "Finalizado"
    },
    {
      "liga": "FC26 R68(CHAMPIONS LEAGUE)20.04.2026",
      "p1": "Liverpool (Luigi)",
      "p2": "Manchester City (MisterX)",
      "placar": "4-2",
      "status": "Finalizado"
    },
    {
      "liga": "FC26 R68(CHAMPIONS LEAGUE)20.04.2026",
      "p1": "Atletico Madrid (Andrew)",
      "p2": "Manchester City (MisterX)",
      "placar": "4-1",
      "status": "Finalizado"
    },
    {
      "liga": "FC26 R68(CHAMPIONS LEAGUE)20.04.2026",
      "p1": "Barcelona (Mateo)",
      "p2": "Real Madrid (VanGogh)",
      "placar": "3-3",
      "status": "Finalizado"
    },
    {
      "liga": "FC26 R69(INTERNATIONAL)20.04.2026",
      "p1": "Argentina (Flash)",
      "p2": "Norway (Alexis)",
      "placar": "4-2",
      "status": "Finalizado"
    },
    {
      "liga": "FC26 R69(INTERNATIONAL)20.04.2026",
      "p1": "France (Cleo)",
      "p2": "Holland (Leonardo)",
      "placar": "4-6",
      "status": "Finalizado"
    },
    {
      "liga": "FC26 R69(INTERNATIONAL)20.04.2026",
      "p1": "Denmark (Gabriel)",
      "p2": "Holland (Leonardo)",
      "placar": "4-3",
      "status": "Finalizado"
    },
    {
      "liga": "FC26 R69(INTERNATIONAL)20.04.2026",
      "p1": "France (Cleo)",
      "p2": "Argentina (Flash)",
      "placar": "2-4",
      "status": "Finalizado"
    },
    {
      "liga": "FC26 R69(INTERNATIONAL)20.04.2026",
      "p1": "Denmark (Gabriel)",
      "p2": "Norway (Alexis)",
      "placar": "3-3",
      "status": "Finalizado"
    },
    {
      "liga": "FC26 R69(INTERNATIONAL)20.04.2026",
      "p1": "Holland (Leonardo)",
      "p2": "Argentina (Flash)",
      "placar": "3-6",
      "status": "Finalizado"
    },
    {
      "liga": "FC26 R69(INTERNATIONAL)20.04.2026",
      "p1": "Denmark (Gabriel)",
      "p2": "Argentina (Flash)",
      "placar": "5-1",
      "status": "Finalizado"
    },
    {
      "liga": "FC26 R69(INTERNATIONAL)20.04.2026",
      "p1": "Norway (Alexis)",
      "p2": "France (Cleo)",
      "placar": "6-4",
      "status": "Finalizado"
    },
    {
      "liga": "FC26 R69(INTERNATIONAL)20.04.2026",
      "p1": "Denmark (Gabriel)",
      "p2": "France (Cleo)",
      "placar": "2-5",
      "status": "Finalizado"
    },
    {
      "liga": "FC26 R69(INTERNATIONAL)20.04.2026",
      "p1": "Norway (Alexis)",
      "p2": "Holland (Leonardo)",
      "placar": "5-1",
      "status": "Finalizado"
    },
    {
      "liga": "FC26 R69(INTERNATIONAL)20.04.2026",
      "p1": "Holland (Leonardo)",
      "p2": "France (Cleo)",
      "placar": "7-4",
      "status": "Finalizado"
    },
    {
      "liga": "FC26 R69(INTERNATIONAL)20.04.2026",
      "p1": "Norway (Alexis)",
      "p2": "Argentina (Flash)",
      "placar": "5-3",
      "status": "Finalizado"
    },
    {
      "liga": "FC26 R69(INTERNATIONAL)20.04.2026",
      "p1": "Argentina (Flash)",
      "p2": "France (Cleo)",
      "placar": "4-1",
      "status": "Finalizado"
    },
    {
      "liga": "FC26 R69(INTERNATIONAL)20.04.2026",
      "p1": "Holland (Leonardo)",
      "p2": "Denmark (Gabriel)",
      "placar": "2-4",
      "status": "Finalizado"
    },
    {
      "liga": "FC26 R69(INTERNATIONAL)20.04.2026",
      "p1": "Argentina (Flash)",
      "p2": "Holland (Leonardo)",
      "placar": "3-6",
      "status": "Finalizado"
    },
    {
      "liga": "FC26 R69(INTERNATIONAL)20.04.2026",
      "p1": "Norway (Alexis)",
      "p2": "Denmark (Gabriel)",
      "placar": "6-4",
      "status": "Finalizado"
    },
    {
      "liga": "FC26 R69(INTERNATIONAL)20.04.2026",
      "p1": "Argentina (Flash)",
      "p2": "Denmark (Gabriel)",
      "placar": "3-1",
      "status": "Finalizado"
    },
    {
      "liga": "FC26 R69(INTERNATIONAL)20.04.2026",
      "p1": "France (Cleo)",
      "p2": "Norway (Alexis)",
      "placar": "4-0",
      "status": "Finalizado"
    },
    {
      "liga": "FC26 R69(INTERNATIONAL)20.04.2026",
      "p1": "France (Cleo)",
      "p2": "Denmark (Gabriel)",
      "placar": "3-2",
      "status": "Finalizado"
    },
    {
      "liga": "FC26 R69(INTERNATIONAL)20.04.2026",
      "p1": "Holland (Leonardo)",
      "p2": "Norway (Alexis)",
      "placar": "3-7",
      "status": "Finalizado"
    },
    {
      "liga": "FC26 R70(LA LIGA)20.04.2026",
      "p1": "Real Betis (Andrew)",
      "p2": "Atletic Bilbao (Mateo)",
      "placar": "5-6",
      "status": "Finalizado"
    },
    {
      "liga": "FC26 R70(LA LIGA)20.04.2026",
      "p1": "Real Madrid (Luigi)",
      "p2": "Barcelona (VanGogh)",
      "placar": "5-3",
      "status": "Finalizado"
    },
    {
      "liga": "FC26 R70(LA LIGA)20.04.2026",
      "p1": "Real Betis (Andrew)",
      "p2": "Real Madrid (Luigi)",
      "placar": "1-4",
      "status": "Finalizado"
    },
    {
      "liga": "FC26 R70(LA LIGA)20.04.2026",
      "p1": "Sevilla (MisterX)",
      "p2": "Atletic Bilbao (Mateo)",
      "placar": "4-3",
      "status": "Finalizado"
    },
    {
      "liga": "FC26 R70(LA LIGA)20.04.2026",
      "p1": "Atletic Bilbao (Mateo)",
      "p2": "Real Madrid (Luigi)",
      "placar": "4-4",
      "status": "Finalizado"
    },
    {
      "liga": "FC26 R70(LA LIGA)20.04.2026",
      "p1": "Sevilla (MisterX)",
      "p2": "Barcelona (VanGogh)",
      "placar": "4-5",
      "status": "Finalizado"
    },
    {
      "liga": "FC26 R70(LA LIGA)20.04.2026",
      "p1": "Barcelona (VanGogh)",
      "p2": "Real Betis (Andrew)",
      "placar": "4-1",
      "status": "Finalizado"
    },
    {
      "liga": "FC26 R70(LA LIGA)20.04.2026",
      "p1": "Sevilla (MisterX)",
      "p2": "Real Madrid (Luigi)",
      "placar": "6-5",
      "status": "Finalizado"
    },
    {
      "liga": "FC26 R70(LA LIGA)20.04.2026",
      "p1": "Barcelona (VanGogh)",
      "p2": "Atletic Bilbao (Mateo)",
      "placar": "1-3",
      "status": "Finalizado"
    },
    {
      "liga": "FC26 R70(LA LIGA)20.04.2026",
      "p1": "Sevilla (MisterX)",
      "p2": "Real Betis (Andrew)",
      "placar": "1-3",
      "status": "Finalizado"
    },
    {
      "liga": "FC26 R70(LA LIGA)20.04.2026",
      "p1": "Atletic Bilbao (Mateo)",
      "p2": "Real Betis (Andrew)",
      "placar": "3-5",
      "status": "Finalizado"
    },
    {
      "liga": "FC26 R70(LA LIGA)20.04.2026",
      "p1": "Barcelona (VanGogh)",
      "p2": "Real Madrid (Luigi)",
      "placar": "5-2",
      "status": "Finalizado"
    },
    {
      "liga": "FC26 R70(LA LIGA)20.04.2026",
      "p1": "Atletic Bilbao (Mateo)",
      "p2": "Sevilla (MisterX)",
      "placar": "3-3",
      "status": "Finalizado"
    },
    {
      "liga": "FC26 R70(LA LIGA)20.04.2026",
      "p1": "Real Madrid (Luigi)",
      "p2": "Real Betis (Andrew)",
      "placar": "3-4",
      "status": "Finalizado"
    },
    {
      "liga": "FC26 R70(LA LIGA)20.04.2026",
      "p1": "Barcelona (VanGogh)",
      "p2": "Sevilla (MisterX)",
      "placar": "2-3",
      "status": "Finalizado"
    },
    {
      "liga": "FC26 R70(LA LIGA)20.04.2026",
      "p1": "Real Madrid (Luigi)",
      "p2": "Atletic Bilbao (Mateo)",
      "placar": "5-2",
      "status": "Finalizado"
    },
    {
      "liga": "FC26 R70(LA LIGA)20.04.2026",
      "p1": "Real Betis (Andrew)",
      "p2": "Barcelona (VanGogh)",
      "placar": "1-4",
      "status": "Finalizado"
    },
    {
      "liga": "FC26 R70(LA LIGA)20.04.2026",
      "p1": "Real Madrid (Luigi)",
      "p2": "Sevilla (MisterX)",
      "placar": "5-2",
      "status": "Finalizado"
    },
    {
      "liga": "FC26 R70(LA LIGA)20.04.2026",
      "p1": "Atletic Bilbao (Mateo)",
      "p2": "Barcelona (VanGogh)",
      "placar": "2-4",
      "status": "Finalizado"
    },
    {
      "liga": "FC26 R70(LA LIGA)20.04.2026",
      "p1": "Real Betis (Andrew)",
      "p2": "Sevilla (MisterX)",
      "placar": "4-1",
      "status": "Finalizado"
    },
    {
      "liga": "FC26 R71(CHAMPIONS LEAGUE)20.04.2026",
      "p1": "PSG (Flash)",
      "p2": "Barcelona (Alexis)",
      "placar": "6-4",
      "status": "Finalizado"
    },
    {
      "liga": "FC26 R71(CHAMPIONS LEAGUE)20.04.2026",
      "p1": "Real Madrid (Cleo)",
      "p2": "Bayern M. (Leonardo)",
      "placar": "3-2",
      "status": "Finalizado"
    },
    {
      "liga": "FC26 R71(CHAMPIONS LEAGUE)20.04.2026",
      "p1": "Atletico Madrid (Gabriel)",
      "p2": "Bayern M. (Leonardo)",
      "placar": "4-1",
      "status": "Finalizado"
    },
    {
      "liga": "FC26 R71(CHAMPIONS LEAGUE)20.04.2026",
      "p1": "Real Madrid (Cleo)",
      "p2": "PSG (Flash)",
      "placar": "0-3",
      "status": "Finalizado"
    },
    {
      "liga": "FC26 R71(CHAMPIONS LEAGUE)20.04.2026",
      "p1": "Atletico Madrid (Gabriel)",
      "p2": "Barcelona (Alexis)",
      "placar": "3-3",
      "status": "Finalizado"
    },
    {
      "liga": "FC26 R71(CHAMPIONS LEAGUE)20.04.2026",
      "p1": "Bayern M. (Leonardo)",
      "p2": "PSG (Flash)",
      "placar": "4-3",
      "status": "Finalizado"
    },
    {
      "liga": "FC26 R71(CHAMPIONS LEAGUE)20.04.2026",
      "p1": "Atletico Madrid (Gabriel)",
      "p2": "PSG (Flash)",
      "placar": "5-4",
      "status": "Finalizado"
    },
    {
      "liga": "FC26 R71(CHAMPIONS LEAGUE)20.04.2026",
      "p1": "Barcelona (Alexis)",
      "p2": "Real Madrid (Cleo)",
      "placar": "4-0",
      "status": "Finalizado"
    },
    {
      "liga": "FC26 R71(CHAMPIONS LEAGUE)20.04.2026",
      "p1": "Atletico Madrid (Gabriel)",
      "p2": "Real Madrid (Cleo)",
      "placar": "4-3",
      "status": "Finalizado"
    },
    {
      "liga": "FC26 R71(CHAMPIONS LEAGUE)20.04.2026",
      "p1": "Barcelona (Alexis)",
      "p2": "Bayern M. (Leonardo)",
      "placar": "5-3",
      "status": "Finalizado"
    },
    {
      "liga": "FC26 R71(CHAMPIONS LEAGUE)20.04.2026",
      "p1": "Barcelona (Alexis)",
      "p2": "PSG (Flash)",
      "placar": "5-1",
      "status": "Finalizado"
    },
    {
      "liga": "FC26 R71(CHAMPIONS LEAGUE)20.04.2026",
      "p1": "Bayern M. (Leonardo)",
      "p2": "Real Madrid (Cleo)",
      "placar": "3-3",
      "status": "Finalizado"
    },
    {
      "liga": "FC26 R71(CHAMPIONS LEAGUE)20.04.2026",
      "p1": "Bayern M. (Leonardo)",
      "p2": "Atletico Madrid (Gabriel)",
      "placar": "6-7",
      "status": "Finalizado"
    },
    {
      "liga": "FC26 R71(CHAMPIONS LEAGUE)20.04.2026",
      "p1": "PSG (Flash)",
      "p2": "Real Madrid (Cleo)",
      "placar": "3-3",
      "status": "Finalizado"
    },
    {
      "liga": "FC26 R71(CHAMPIONS LEAGUE)20.04.2026",
      "p1": "Barcelona (Alexis)",
      "p2": "Atletico Madrid (Gabriel)",
      "placar": "6-2",
      "status": "Finalizado"
    },
    {
      "liga": "FC26 R71(CHAMPIONS LEAGUE)20.04.2026",
      "p1": "PSG (Flash)",
      "p2": "Bayern M. (Leonardo)",
      "placar": "3-3",
      "status": "Finalizado"
    },
    {
      "liga": "FC26 R71(CHAMPIONS LEAGUE)20.04.2026",
      "p1": "PSG (Flash)",
      "p2": "Atletico Madrid (Gabriel)",
      "placar": "5-4",
      "status": "Finalizado"
    },
    {
      "liga": "FC26 R71(CHAMPIONS LEAGUE)20.04.2026",
      "p1": "Real Madrid (Cleo)",
      "p2": "Barcelona (Alexis)",
      "placar": "2-5",
      "status": "Finalizado"
    },
    {
      "liga": "FC26 R71(CHAMPIONS LEAGUE)20.04.2026",
      "p1": "Bayern M. (Leonardo)",
      "p2": "Barcelona (Alexis)",
      "placar": "5-3",
      "status": "Finalizado"
    },
    {
      "liga": "FC26 R71(CHAMPIONS LEAGUE)20.04.2026",
      "p1": "Real Madrid (Cleo)",
      "p2": "Atletico Madrid (Gabriel)",
      "placar": "0-4",
      "status": "Finalizado"
    },
    {
      "liga": "FC26 R72(SERIA A)20.04.2026",
      "p1": "Inter (Luigi)",
      "p2": "Milan (VanGogh)",
      "placar": "4-5",
      "status": "Finalizado"
    },
    {
      "liga": "FC26 R72(SERIA A)20.04.2026",
      "p1": "Napoli (Andrew)",
      "p2": "Lazio (Mateo)",
      "placar": "3-1",
      "status": "Finalizado"
    },
    {
      "liga": "FC26 R72(SERIA A)20.04.2026",
      "p1": "Juventus (MisterX)",
      "p2": "Lazio (Mateo)",
      "placar": "5-3",
      "status": "Finalizado"
    },
    {
      "liga": "FC26 R72(SERIA A)20.04.2026",
      "p1": "Napoli (Andrew)",
      "p2": "Inter (Luigi)",
      "placar": "5-3",
      "status": "Finalizado"
    },
    {
      "liga": "FC26 R72(SERIA A)20.04.2026",
      "p1": "Juventus (MisterX)",
      "p2": "Milan (VanGogh)",
      "placar": "2-6",
      "status": "Finalizado"
    },
    {
      "liga": "FC26 R72(SERIA A)20.04.2026",
      "p1": "Lazio (Mateo)",
      "p2": "Inter (Luigi)",
      "placar": "4-2",
      "status": "Finalizado"
    },
    {
      "liga": "FC26 R72(SERIA A)20.04.2026",
      "p1": "Juventus (MisterX)",
      "p2": "Inter (Luigi)",
      "placar": "6-5",
      "status": "Finalizado"
    },
    {
      "liga": "FC26 R72(SERIA A)20.04.2026",
      "p1": "Milan (VanGogh)",
      "p2": "Napoli (Andrew)",
      "placar": "2-2",
      "status": "Finalizado"
    },
    {
      "liga": "FC26 R72(SERIA A)20.04.2026",
      "p1": "Juventus (MisterX)",
      "p2": "Napoli (Andrew)",
      "placar": "3-5",
      "status": "Finalizado"
    },
    {
      "liga": "FC26 R72(SERIA A)20.04.2026",
      "p1": "Milan (VanGogh)",
      "p2": "Lazio (Mateo)",
      "placar": "0-4",
      "status": "Finalizado"
    },
    {
      "liga": "FC26 R72(SERIA A)20.04.2026",
      "p1": "Lazio (Mateo)",
      "p2": "Napoli (Andrew)",
      "placar": "2-3",
      "status": "Finalizado"
    },
    {
      "liga": "FC26 R72(SERIA A)20.04.2026",
      "p1": "Milan (VanGogh)",
      "p2": "Inter (Luigi)",
      "placar": "1-5",
      "status": "Finalizado"
    },
    {
      "liga": "FC26 R72(SERIA A)20.04.2026",
      "p1": "Inter (Luigi)",
      "p2": "Napoli (Andrew)",
      "placar": "2-3",
      "status": "Finalizado"
    },
    {
      "liga": "FC26 R72(SERIA A)20.04.2026",
      "p1": "Lazio (Mateo)",
      "p2": "Juventus (MisterX)",
      "placar": "6-5",
      "status": "Finalizado"
    },
    {
      "liga": "FC26 R72(SERIA A)20.04.2026",
      "p1": "Inter (Luigi)",
      "p2": "Lazio (Mateo)",
      "placar": "3-3",
      "status": "Finalizado"
    },
    {
      "liga": "FC26 R72(SERIA A)20.04.2026",
      "p1": "Milan (VanGogh)",
      "p2": "Juventus (MisterX)",
      "placar": "5-1",
      "status": "Finalizado"
    },
    {
      "liga": "FC26 R72(SERIA A)20.04.2026",
      "p1": "Inter (Luigi)",
      "p2": "Juventus (MisterX)",
      "placar": "6-4",
      "status": "Finalizado"
    },
    {
      "liga": "FC26 R72(SERIA A)20.04.2026",
      "p1": "Napoli (Andrew)",
      "p2": "Milan (VanGogh)",
      "placar": "3-3",
      "status": "Finalizado"
    },
    {
      "liga": "FC26 R72(SERIA A)20.04.2026",
      "p1": "Lazio (Mateo)",
      "p2": "Milan (VanGogh)",
      "placar": "4-3",
      "status": "Finalizado"
    },
    {
      "liga": "FC26 R72(SERIA A)20.04.2026",
      "p1": "Napoli (Andrew)",
      "p2": "Juventus (MisterX)",
      "placar": "7-4",
      "status": "Finalizado"
    },
    {
      "liga": "FC26 R73(INTERNATIONAL)20.04.2026",
      "p1": "Denmark (Noah)",
      "p2": "Portugal (Oliver)",
      "placar": "2-3",
      "status": "Finalizado"
    },
    {
      "liga": "FC26 R73(INTERNATIONAL)20.04.2026",
      "p1": "Holland (Liam)",
      "p2": "Argentina (Donatello)",
      "placar": "1-3",
      "status": "Finalizado"
    },
    {
      "liga": "FC26 R73(INTERNATIONAL)20.04.2026",
      "p1": "France (Logan)",
      "p2": "Argentina (Donatello)",
      "placar": "3-4",
      "status": "Finalizado"
    },
    {
      "liga": "FC26 R73(INTERNATIONAL)20.04.2026",
      "p1": "Holland (Liam)",
      "p2": "Denmark (Noah)",
      "placar": "6-5",
      "status": "Finalizado"
    },
    {
      "liga": "FC26 R73(INTERNATIONAL)20.04.2026",
      "p1": "Argentina (Donatello)",
      "p2": "Denmark (Noah)",
      "placar": "7-4",
      "status": "Finalizado"
    },
    {
      "liga": "FC26 R73(INTERNATIONAL)20.04.2026",
      "p1": "France (Logan)",
      "p2": "Portugal (Oliver)",
      "placar": "3-3",
      "status": "Finalizado"
    },
    {
      "liga": "FC26 R73(INTERNATIONAL)20.04.2026",
      "p1": "France (Logan)",
      "p2": "Denmark (Noah)",
      "placar": "2-4",
      "status": "Finalizado"
    },
    {
      "liga": "FC26 R73(INTERNATIONAL)20.04.2026",
      "p1": "Portugal (Oliver)",
      "p2": "Holland (Liam)",
      "placar": "2-2",
      "status": "Finalizado"
    },
    {
      "liga": "FC26 R73(INTERNATIONAL)20.04.2026",
      "p1": "France (Logan)",
      "p2": "Holland (Liam)",
      "placar": "4-2",
      "status": "Finalizado"
    },
    {
      "liga": "FC26 R73(INTERNATIONAL)20.04.2026",
      "p1": "Portugal (Oliver)",
      "p2": "Argentina (Donatello)",
      "placar": "2-2",
      "status": "Finalizado"
    },
    {
      "liga": "FC26 R73(INTERNATIONAL)20.04.2026",
      "p1": "Argentina (Donatello)",
      "p2": "Holland (Liam)",
      "placar": "3-5",
      "status": "Finalizado"
    },
    {
      "liga": "FC26 R73(INTERNATIONAL)20.04.2026",
      "p1": "Portugal (Oliver)",
      "p2": "Denmark (Noah)",
      "placar": "3-2",
      "status": "Finalizado"
    },
    {
      "liga": "FC26 R73(INTERNATIONAL)20.04.2026",
      "p1": "Argentina (Donatello)",
      "p2": "France (Logan)",
      "placar": "3-1",
      "status": "Finalizado"
    },
    {
      "liga": "FC26 R73(INTERNATIONAL)20.04.2026",
      "p1": "Denmark (Noah)",
      "p2": "Holland (Liam)",
      "placar": "6-2",
      "status": "Finalizado"
    },
    {
      "liga": "FC26 R73(INTERNATIONAL)20.04.2026",
      "p1": "Denmark (Noah)",
      "p2": "Argentina (Donatello)",
      "placar": "4-2",
      "status": "Finalizado"
    },
    {
      "liga": "FC26 R73(INTERNATIONAL)20.04.2026",
      "p1": "Portugal (Oliver)",
      "p2": "France (Logan)",
      "placar": "4-2",
      "status": "Finalizado"
    },
    {
      "liga": "FC26 R73(INTERNATIONAL)20.04.2026",
      "p1": "Denmark (Noah)",
      "p2": "France (Logan)",
      "placar": "3-3",
      "status": "Finalizado"
    },
    {
      "liga": "FC26 R73(INTERNATIONAL)20.04.2026",
      "p1": "Holland (Liam)",
      "p2": "Portugal (Oliver)",
      "placar": "3-3",
      "status": "Finalizado"
    },
    {
      "liga": "FC26 R73(INTERNATIONAL)20.04.2026",
      "p1": "Argentina (Donatello)",
      "p2": "Portugal (Oliver)",
      "placar": "4-4",
      "status": "Finalizado"
    },
    {
      "liga": "FC26 R73(INTERNATIONAL)20.04.2026",
      "p1": "Holland (Liam)",
      "p2": "France (Logan)",
      "placar": "5-2",
      "status": "Finalizado"
    },
    {
      "liga": "FC26 R74(CHAMPIONS LEAGUE)20.04.2026",
      "p1": "Atletico Madrid (Dominic)",
      "p2": "Barcelona (Kai)",
      "placar": "3-3",
      "status": "Finalizado"
    },
    {
      "liga": "FC26 R74(CHAMPIONS LEAGUE)20.04.2026",
      "p1": "Real Madrid (George)",
      "p2": "Bayern M. (Juan)",
      "placar": "3-1",
      "status": "Finalizado"
    },
    {
      "liga": "FC26 R74(CHAMPIONS LEAGUE)20.04.2026",
      "p1": "PSG (Beckham)",
      "p2": "Bayern M. (Juan)",
      "placar": "7-3",
      "status": "Finalizado"
    },
    {
      "liga": "FC26 R74(CHAMPIONS LEAGUE)20.04.2026",
      "p1": "Real Madrid (George)",
      "p2": "Atletico Madrid (Dominic)",
      "placar": "3-3",
      "status": "Finalizado"
    },
    {
      "liga": "FC26 R74(CHAMPIONS LEAGUE)20.04.2026",
      "p1": "Bayern M. (Juan)",
      "p2": "Atletico Madrid (Dominic)",
      "placar": "2-7",
      "status": "Finalizado"
    },
    {
      "liga": "FC26 R74(CHAMPIONS LEAGUE)20.04.2026",
      "p1": "PSG (Beckham)",
      "p2": "Barcelona (Kai)",
      "placar": "1-3",
      "status": "Finalizado"
    },
    {
      "liga": "FC26 R74(CHAMPIONS LEAGUE)20.04.2026",
      "p1": "Barcelona (Kai)",
      "p2": "Real Madrid (George)",
      "placar": "3-1",
      "status": "Finalizado"
    },
    {
      "liga": "FC26 R74(CHAMPIONS LEAGUE)20.04.2026",
      "p1": "PSG (Beckham)",
      "p2": "Atletico Madrid (Dominic)",
      "placar": "6-4",
      "status": "Finalizado"
    },
    {
      "liga": "FC26 R74(CHAMPIONS LEAGUE)20.04.2026",
      "p1": "Barcelona (Kai)",
      "p2": "Bayern M. (Juan)",
      "placar": "1-2",
      "status": "Finalizado"
    },
    {
      "liga": "FC26 R74(CHAMPIONS LEAGUE)20.04.2026",
      "p1": "PSG (Beckham)",
      "p2": "Real Madrid (George)",
      "placar": "2-1",
      "status": "Finalizado"
    },
    {
      "liga": "FC26 R74(CHAMPIONS LEAGUE)20.04.2026",
      "p1": "Barcelona (Kai)",
      "p2": "Atletico Madrid (Dominic)",
      "placar": "1-1",
      "status": "Finalizado"
    },
    {
      "liga": "FC26 R74(CHAMPIONS LEAGUE)20.04.2026",
      "p1": "Bayern M. (Juan)",
      "p2": "Real Madrid (George)",
      "placar": "2-2",
      "status": "Finalizado"
    },
    {
      "liga": "FC26 R74(CHAMPIONS LEAGUE)20.04.2026",
      "p1": "Atletico Madrid (Dominic)",
      "p2": "Real Madrid (George)",
      "placar": "3-3",
      "status": "Finalizado"
    },
    {
      "liga": "FC26 R74(CHAMPIONS LEAGUE)20.04.2026",
      "p1": "Bayern M. (Juan)",
      "p2": "PSG (Beckham)",
      "placar": "3-7",
      "status": "Finalizado"
    },
    {
      "liga": "FC26 R74(CHAMPIONS LEAGUE)20.04.2026",
      "p1": "Atletico Madrid (Dominic)",
      "p2": "Bayern M. (Juan)",
      "placar": "2-1",
      "status": "Finalizado"
    },
    {
      "liga": "FC26 R74(CHAMPIONS LEAGUE)20.04.2026",
      "p1": "Barcelona (Kai)",
      "p2": "PSG (Beckham)",
      "placar": "5-2",
      "status": "Finalizado"
    },
    {
      "liga": "FC26 R74(CHAMPIONS LEAGUE)20.04.2026",
      "p1": "Atletico Madrid (Dominic)",
      "p2": "PSG (Beckham)",
      "placar": "4-7",
      "status": "Finalizado"
    },
    {
      "liga": "FC26 R74(CHAMPIONS LEAGUE)20.04.2026",
      "p1": "Real Madrid (George)",
      "p2": "Barcelona (Kai)",
      "placar": "0-3",
      "status": "Finalizado"
    },
    {
      "liga": "FC26 R74(CHAMPIONS LEAGUE)20.04.2026",
      "p1": "Bayern M. (Juan)",
      "p2": "Barcelona (Kai)",
      "placar": "2-2",
      "status": "Finalizado"
    },
    {
      "liga": "FC26 R74(CHAMPIONS LEAGUE)20.04.2026",
      "p1": "Real Madrid (George)",
      "p2": "PSG (Beckham)",
      "placar": "5-6",
      "status": "Finalizado"
    },
    {
      "liga": "FC26 R75(SERIA A)20.04.2026",
      "p1": "Atalanta (Noah)",
      "p2": "Napoli (Oliver)",
      "placar": "4-2",
      "status": "Finalizado"
    },
    {
      "liga": "FC26 R75(SERIA A)20.04.2026",
      "p1": "Inter (Liam)",
      "p2": "Lazio (Donatello)",
      "placar": "1-2",
      "status": "Finalizado"
    },
    {
      "liga": "FC26 R75(SERIA A)20.04.2026",
      "p1": "Inter (Liam)",
      "p2": "Atalanta (Noah)",
      "placar": "3-5",
      "status": "Finalizado"
    },
    {
      "liga": "FC26 R75(SERIA A)20.04.2026",
      "p1": "Milan (Logan)",
      "p2": "Lazio (Donatello)",
      "placar": "4-2",
      "status": "Finalizado"
    },
    {
      "liga": "FC26 R75(SERIA A)20.04.2026",
      "p1": "Lazio (Donatello)",
      "p2": "Atalanta (Noah)",
      "placar": "1-5",
      "status": "Finalizado"
    },
    {
      "liga": "FC26 R75(SERIA A)20.04.2026",
      "p1": "Milan (Logan)",
      "p2": "Napoli (Oliver)",
      "placar": "2-4",
      "status": "Finalizado"
    },
    {
      "liga": "FC26 R75(SERIA A)20.04.2026",
      "p1": "Milan (Logan)",
      "p2": "Atalanta (Noah)",
      "placar": "4-1",
      "status": "Finalizado"
    },
    {
      "liga": "FC26 R75(SERIA A)20.04.2026",
      "p1": "Napoli (Oliver)",
      "p2": "Inter (Liam)",
      "placar": "6-4",
      "status": "Finalizado"
    },
    {
      "liga": "FC26 R75(SERIA A)20.04.2026",
      "p1": "Milan (Logan)",
      "p2": "Inter (Liam)",
      "placar": "2-1",
      "status": "Finalizado"
    },
    {
      "liga": "FC26 R75(SERIA A)20.04.2026",
      "p1": "Napoli (Oliver)",
      "p2": "Lazio (Donatello)",
      "placar": "4-2",
      "status": "Finalizado"
    },
    {
      "liga": "FC26 R75(SERIA A)20.04.2026",
      "p1": "Lazio (Donatello)",
      "p2": "Inter (Liam)",
      "placar": "3-0",
      "status": "Finalizado"
    },
    {
      "liga": "FC26 R75(SERIA A)20.04.2026",
      "p1": "Napoli (Oliver)",
      "p2": "Atalanta (Noah)",
      "placar": "5-3",
      "status": "Finalizado"
    },
    {
      "liga": "FC26 R75(SERIA A)20.04.2026",
      "p1": "Atalanta (Noah)",
      "p2": "Inter (Liam)",
      "placar": "5-3",
      "status": "Finalizado"
    },
    {
      "liga": "FC26 R75(SERIA A)20.04.2026",
      "p1": "Lazio (Donatello)",
      "p2": "Milan (Logan)",
      "placar": "1-3",
      "status": "Finalizado"
    },
    {
      "liga": "FC26 R75(SERIA A)20.04.2026",
      "p1": "Atalanta (Noah)",
      "p2": "Lazio (Donatello)",
      "placar": "2-2",
      "status": "Finalizado"
    },
    {
      "liga": "FC26 R75(SERIA A)20.04.2026",
      "p1": "Napoli (Oliver)",
      "p2": "Milan (Logan)",
      "placar": "2-2",
      "status": "Finalizado"
    },
    {
      "liga": "FC26 R75(SERIA A)20.04.2026",
      "p1": "Atalanta (Noah)",
      "p2": "Milan (Logan)",
      "placar": "4-4",
      "status": "Finalizado"
    },
    {
      "liga": "FC26 R75(SERIA A)20.04.2026",
      "p1": "Inter (Liam)",
      "p2": "Napoli (Oliver)",
      "placar": "4-3",
      "status": "Finalizado"
    },
    {
      "liga": "FC26 R75(SERIA A)20.04.2026",
      "p1": "Inter (Liam)",
      "p2": "Milan (Logan)",
      "placar": "vs",
      "status": "Agendado"
    },
    {
      "liga": "FC26 R75(SERIA A)20.04.2026",
      "p1": "Lazio (Donatello)",
      "p2": "Napoli (Oliver)",
      "placar": "vs",
      "status": "Agendado"
    },
    {
      "liga": "FC26 R76(LA LIGA)20.04.2026",
      "p1": "Barcelona (George)",
      "p2": "Real Madrid (Juan)",
      "placar": "2-3",
      "status": "Finalizado"
    },
    {
      "liga": "FC26 R76(LA LIGA)20.04.2026",
      "p1": "Real Betis (Dominic)",
      "p2": "Athletic Bilbao (Kai)",
      "placar": "6-2",
      "status": "Finalizado"
    },
    {
      "liga": "FC26 R76(LA LIGA)20.04.2026",
      "p1": "Barcelona (George)",
      "p2": "Real Betis (Dominic)",
      "placar": "1-0",
      "status": "Finalizado"
    },
    {
      "liga": "FC26 R76(LA LIGA)20.04.2026",
      "p1": "Real Sociedad (Beckham)",
      "p2": "Real Madrid (Juan)",
      "placar": "0-3",
      "status": "Finalizado"
    },
    {
      "liga": "FC26 R76(LA LIGA)20.04.2026",
      "p1": "Real Madrid (Juan)",
      "p2": "Real Betis (Dominic)",
      "placar": "1-7",
      "status": "Finalizado"
    },
    {
      "liga": "FC26 R76(LA LIGA)20.04.2026",
      "p1": "Real Sociedad (Beckham)",
      "p2": "Athletic Bilbao (Kai)",
      "placar": "1-3",
      "status": "Finalizado"
    },
    {
      "liga": "FC26 R76(LA LIGA)20.04.2026",
      "p1": "Athletic Bilbao (Kai)",
      "p2": "Barcelona (George)",
      "placar": "1-2",
      "status": "Finalizado"
    },
    {
      "liga": "FC26 R76(LA LIGA)20.04.2026",
      "p1": "Real Sociedad (Beckham)",
      "p2": "Real Betis (Dominic)",
      "placar": "5-6",
      "status": "Finalizado"
    },
    {
      "liga": "FC26 R76(LA LIGA)20.04.2026",
      "p1": "Athletic Bilbao (Kai)",
      "p2": "Real Madrid (Juan)",
      "placar": "1-2",
      "status": "Finalizado"
    },
    {
      "liga": "FC26 R76(LA LIGA)20.04.2026",
      "p1": "Real Sociedad (Beckham)",
      "p2": "Barcelona (George)",
      "placar": "4-3",
      "status": "Finalizado"
    },
    {
      "liga": "FC26 R76(LA LIGA)20.04.2026",
      "p1": "Athletic Bilbao (Kai)",
      "p2": "Real Betis (Dominic)",
      "placar": "3-5",
      "status": "Finalizado"
    },
    {
      "liga": "FC26 R76(LA LIGA)20.04.2026",
      "p1": "Real Madrid (Juan)",
      "p2": "Barcelona (George)",
      "placar": "1-2",
      "status": "Finalizado"
    },
    {
      "liga": "FC26 R76(LA LIGA)20.04.2026",
      "p1": "Real Betis (Dominic)",
      "p2": "Barcelona (George)",
      "placar": "4-3",
      "status": "Finalizado"
    },
    {
      "liga": "FC26 R76(LA LIGA)20.04.2026",
      "p1": "Real Madrid (Juan)",
      "p2": "Real Sociedad (Beckham)",
      "placar": "6-4",
      "status": "Finalizado"
    },
    {
      "liga": "FC26 R76(LA LIGA)20.04.2026",
      "p1": "Athletic Bilbao (Kai)",
      "p2": "Real Sociedad (Beckham)",
      "placar": "4-4",
      "status": "Finalizado"
    },
    {
      "liga": "FC26 R76(LA LIGA)20.04.2026",
      "p1": "Real Betis (Dominic)",
      "p2": "Real Madrid (Juan)",
      "placar": "4-1",
      "status": "Finalizado"
    },
    {
      "liga": "FC26 R76(LA LIGA)20.04.2026",
      "p1": "Barcelona (George)",
      "p2": "Athletic Bilbao (Kai)",
      "placar": "vs",
      "status": "Agendado"
    },
    {
      "liga": "FC26 R76(LA LIGA)20.04.2026",
      "p1": "Real Betis (Dominic)",
      "p2": "Real Sociedad (Beckham)",
      "placar": "vs",
      "status": "Agendado"
    },
    {
      "liga": "FC26 R76(LA LIGA)20.04.2026",
      "p1": "Barcelona (George)",
      "p2": "Real Sociedad (Beckham)",
      "placar": "vs",
      "status": "Agendado"
    },
    {
      "liga": "FC26 R76(LA LIGA)20.04.2026",
      "p1": "Real Madrid (Juan)",
      "p2": "Athletic Bilbao (Kai)",
      "placar": "vs",
      "status": "Agendado"
    },
    {
      "liga": "FC26 R77(CHAMPIONS LEAGUE)20.04.2026",
      "p1": "Barcelona (Noah)",
      "p2": "Liverpool (Oliver)",
      "placar": "vs",
      "status": "Agendado"
    },
    {
      "liga": "FC26 R77(CHAMPIONS LEAGUE)20.04.2026",
      "p1": "Bayern M. (Liam)",
      "p2": "PSG (Donatello)",
      "placar": "vs",
      "status": "Agendado"
    },
    {
      "liga": "FC26 R77(CHAMPIONS LEAGUE)20.04.2026",
      "p1": "Bayern M. (Liam)",
      "p2": "Barcelona (Noah)",
      "placar": "vs",
      "status": "Agendado"
    },
    {
      "liga": "FC26 R77(CHAMPIONS LEAGUE)20.04.2026",
      "p1": "Real Madrid (Logan)",
      "p2": "PSG (Donatello)",
      "placar": "vs",
      "status": "Agendado"
    },
    {
      "liga": "FC26 R77(CHAMPIONS LEAGUE)20.04.2026",
      "p1": "PSG (Donatello)",
      "p2": "Barcelona (Noah)",
      "placar": "vs",
      "status": "Agendado"
    },
    {
      "liga": "FC26 R77(CHAMPIONS LEAGUE)20.04.2026",
      "p1": "Real Madrid (Logan)",
      "p2": "Liverpool (Oliver)",
      "placar": "vs",
      "status": "Agendado"
    },
    {
      "liga": "FC26 R77(CHAMPIONS LEAGUE)20.04.2026",
      "p1": "Liverpool (Oliver)",
      "p2": "Bayern M. (Liam)",
      "placar": "vs",
      "status": "Agendado"
    },
    {
      "liga": "FC26 R77(CHAMPIONS LEAGUE)20.04.2026",
      "p1": "Real Madrid (Logan)",
      "p2": "Barcelona (Noah)",
      "placar": "vs",
      "status": "Agendado"
    },
    {
      "liga": "FC26 R77(CHAMPIONS LEAGUE)20.04.2026",
      "p1": "Liverpool (Oliver)",
      "p2": "PSG (Donatello)",
      "placar": "vs",
      "status": "Agendado"
    },
    {
      "liga": "FC26 R77(CHAMPIONS LEAGUE)20.04.2026",
      "p1": "Real Madrid (Logan)",
      "p2": "Bayern M. (Liam)",
      "placar": "vs",
      "status": "Agendado"
    },
    {
      "liga": "FC26 R77(CHAMPIONS LEAGUE)20.04.2026",
      "p1": "Liverpool (Oliver)",
      "p2": "Barcelona (Noah)",
      "placar": "vs",
      "status": "Agendado"
    },
    {
      "liga": "FC26 R77(CHAMPIONS LEAGUE)20.04.2026",
      "p1": "PSG (Donatello)",
      "p2": "Bayern M. (Liam)",
      "placar": "vs",
      "status": "Agendado"
    },
    {
      "liga": "FC26 R77(CHAMPIONS LEAGUE)20.04.2026",
      "p1": "Barcelona (Noah)",
      "p2": "Bayern M. (Liam)",
      "placar": "vs",
      "status": "Agendado"
    },
    {
      "liga": "FC26 R77(CHAMPIONS LEAGUE)20.04.2026",
      "p1": "PSG (Donatello)",
      "p2": "Real Madrid (Logan)",
      "placar": "vs",
      "status": "Agendado"
    },
    {
      "liga": "FC26 R77(CHAMPIONS LEAGUE)20.04.2026",
      "p1": "Barcelona (Noah)",
      "p2": "PSG (Donatello)",
      "placar": "vs",
      "status": "Agendado"
    },
    {
      "liga": "FC26 R77(CHAMPIONS LEAGUE)20.04.2026",
      "p1": "Liverpool (Oliver)",
      "p2": "Real Madrid (Logan)",
      "placar": "vs",
      "status": "Agendado"
    },
    {
      "liga": "FC26 R77(CHAMPIONS LEAGUE)20.04.2026",
      "p1": "Barcelona (Noah)",
      "p2": "Real Madrid (Logan)",
      "placar": "vs",
      "status": "Agendado"
    },
    {
      "liga": "FC26 R77(CHAMPIONS LEAGUE)20.04.2026",
      "p1": "Bayern M. (Liam)",
      "p2": "Liverpool (Oliver)",
      "placar": "vs",
      "status": "Agendado"
    },
    {
      "liga": "FC26 R77(CHAMPIONS LEAGUE)20.04.2026",
      "p1": "Bayern M. (Liam)",
      "p2": "Real Madrid (Logan)",
      "placar": "vs",
      "status": "Agendado"
    },
    {
      "liga": "FC26 R77(CHAMPIONS LEAGUE)20.04.2026",
      "p1": "PSG (Donatello)",
      "p2": "Liverpool (Oliver)",
      "placar": "vs",
      "status": "Agendado"
    },
    {
      "liga": "FC26 R78(PREMIER LEAGUE)20.04.2026",
      "p1": "Chelsea (Dominic)",
      "p2": "Aston Villa (Kai)",
      "placar": "vs",
      "status": "Agendado"
    },
    {
      "liga": "FC26 R78(PREMIER LEAGUE)20.04.2026",
      "p1": "Manchester City (George)",
      "p2": "Liverpool (Juan)",
      "placar": "vs",
      "status": "Agendado"
    },
    {
      "liga": "FC26 R78(PREMIER LEAGUE)20.04.2026",
      "p1": "Arsenal (Beckham)",
      "p2": "Liverpool (Juan)",
      "placar": "vs",
      "status": "Agendado"
    },
    {
      "liga": "FC26 R78(PREMIER LEAGUE)20.04.2026",
      "p1": "Manchester City (George)",
      "p2": "Chelsea (Dominic)",
      "placar": "vs",
      "status": "Agendado"
    },
    {
      "liga": "FC26 R78(PREMIER LEAGUE)20.04.2026",
      "p1": "Arsenal (Beckham)",
      "p2": "Aston Villa (Kai)",
      "placar": "vs",
      "status": "Agendado"
    },
    {
      "liga": "FC26 R78(PREMIER LEAGUE)20.04.2026",
      "p1": "Liverpool (Juan)",
      "p2": "Chelsea (Dominic)",
      "placar": "vs",
      "status": "Agendado"
    },
    {
      "liga": "FC26 R78(PREMIER LEAGUE)20.04.2026",
      "p1": "Arsenal (Beckham)",
      "p2": "Chelsea (Dominic)",
      "placar": "vs",
      "status": "Agendado"
    },
    {
      "liga": "FC26 R78(PREMIER LEAGUE)20.04.2026",
      "p1": "Aston Villa (Kai)",
      "p2": "Manchester City (George)",
      "placar": "vs",
      "status": "Agendado"
    },
    {
      "liga": "FC26 R78(PREMIER LEAGUE)20.04.2026",
      "p1": "Arsenal (Beckham)",
      "p2": "Manchester City (George)",
      "placar": "vs",
      "status": "Agendado"
    },
    {
      "liga": "FC26 R78(PREMIER LEAGUE)20.04.2026",
      "p1": "Aston Villa (Kai)",
      "p2": "Liverpool (Juan)",
      "placar": "vs",
      "status": "Agendado"
    },
    {
      "liga": "FC26 R78(PREMIER LEAGUE)20.04.2026",
      "p1": "Aston Villa (Kai)",
      "p2": "Chelsea (Dominic)",
      "placar": "vs",
      "status": "Agendado"
    },
    {
      "liga": "FC26 R78(PREMIER LEAGUE)20.04.2026",
      "p1": "Liverpool (Juan)",
      "p2": "Manchester City (George)",
      "placar": "vs",
      "status": "Agendado"
    },
    {
      "liga": "FC26 R78(PREMIER LEAGUE)20.04.2026",
      "p1": "Chelsea (Dominic)",
      "p2": "Manchester City (George)",
      "placar": "vs",
      "status": "Agendado"
    },
    {
      "liga": "FC26 R78(PREMIER LEAGUE)20.04.2026",
      "p1": "Liverpool (Juan)",
      "p2": "Arsenal (Beckham)",
      "placar": "vs",
      "status": "Agendado"
    },
    {
      "liga": "FC26 R78(PREMIER LEAGUE)20.04.2026",
      "p1": "Aston Villa (Kai)",
      "p2": "Arsenal (Beckham)",
      "placar": "vs",
      "status": "Agendado"
    },
    {
      "liga": "FC26 R78(PREMIER LEAGUE)20.04.2026",
      "p1": "Chelsea (Dominic)",
      "p2": "Liverpool (Juan)",
      "placar": "vs",
      "status": "Agendado"
    },
    {
      "liga": "FC26 R78(PREMIER LEAGUE)20.04.2026",
      "p1": "Chelsea (Dominic)",
      "p2": "Arsenal (Beckham)",
      "placar": "vs",
      "status": "Agendado"
    },
    {
      "liga": "FC26 R78(PREMIER LEAGUE)20.04.2026",
      "p1": "Manchester City (George)",
      "p2": "Aston Villa (Kai)",
      "placar": "vs",
      "status": "Agendado"
    },
    {
      "liga": "FC26 R78(PREMIER LEAGUE)20.04.2026",
      "p1": "Liverpool (Juan)",
      "p2": "Aston Villa (Kai)",
      "placar": "vs",
      "status": "Agendado"
    },
    {
      "liga": "FC26 R78(PREMIER LEAGUE)20.04.2026",
      "p1": "Manchester City (George)",
      "p2": "Arsenal (Beckham)",
      "placar": "vs",
      "status": "Agendado"
    },
    {
      "liga": "FC26 R79(CHAMPIONS LEAGUE)20.04.2026",
      "p1": "Bayern M. (Conde)",
      "p2": "Real Madrid (Arthur)",
      "placar": "vs",
      "status": "Agendado"
    },
    {
      "liga": "FC26 R79(CHAMPIONS LEAGUE)20.04.2026",
      "p1": "Liverpool (Dexter)",
      "p2": "Borussia Dortmund (Odin)",
      "placar": "vs",
      "status": "Agendado"
    },
    {
      "liga": "FC26 R79(CHAMPIONS LEAGUE)20.04.2026",
      "p1": "Bayer Leverkusen (Matrix)",
      "p2": "Borussia Dortmund (Odin)",
      "placar": "vs",
      "status": "Agendado"
    },
    {
      "liga": "FC26 R79(CHAMPIONS LEAGUE)20.04.2026",
      "p1": "Liverpool (Dexter)",
      "p2": "Bayern M. (Conde)",
      "placar": "vs",
      "status": "Agendado"
    },
    {
      "liga": "FC26 R79(CHAMPIONS LEAGUE)20.04.2026",
      "p1": "Bayer Leverkusen (Matrix)",
      "p2": "Real Madrid (Arthur)",
      "placar": "vs",
      "status": "Agendado"
    },
    {
      "liga": "FC26 R79(CHAMPIONS LEAGUE)20.04.2026",
      "p1": "Borussia Dortmund (Odin)",
      "p2": "Bayern M. (Conde)",
      "placar": "vs",
      "status": "Agendado"
    },
    {
      "liga": "FC26 R79(CHAMPIONS LEAGUE)20.04.2026",
      "p1": "Bayer Leverkusen (Matrix)",
      "p2": "Bayern M. (Conde)",
      "placar": "vs",
      "status": "Agendado"
    },
    {
      "liga": "FC26 R79(CHAMPIONS LEAGUE)20.04.2026",
      "p1": "Real Madrid (Arthur)",
      "p2": "Liverpool (Dexter)",
      "placar": "vs",
      "status": "Agendado"
    },
    {
      "liga": "FC26 R80(INTERNATIONAL)20.04.2026",
      "p1": "Portugal (Sebastian)",
      "p2": "Holland (Felix)",
      "placar": "vs",
      "status": "Agendado"
    },
    {
      "liga": "FC26 R80(INTERNATIONAL)20.04.2026",
      "p1": "Spain (Eric)",
      "p2": "France (Haidan)",
      "placar": "vs",
      "status": "Agendado"
    },
    {
      "liga": "FC26 R80(INTERNATIONAL)20.04.2026",
      "p1": "Argentina (Iron)",
      "p2": "France (Haidan)",
      "placar": "vs",
      "status": "Agendado"
    },
    {
      "liga": "FC26 R80(INTERNATIONAL)20.04.2026",
      "p1": "Spain (Eric)",
      "p2": "Portugal (Sebastian)",
      "placar": "vs",
      "status": "Agendado"
    },
    {
      "liga": "FC26 R80(INTERNATIONAL)20.04.2026",
      "p1": "Argentina (Iron)",
      "p2": "Holland (Felix)",
      "placar": "vs",
      "status": "Agendado"
    },
    {
      "liga": "FC26 R80(INTERNATIONAL)20.04.2026",
      "p1": "France (Haidan)",
      "p2": "Portugal (Sebastian)",
      "placar": "vs",
      "status": "Agendado"
    }
  ],
  "resumo": {
    "FC26 R61(CHAMPIONS LEAGUE)19.04.2026": {
      "total": 12,
      "finalizados": 12,
      "agendados": 0
    },
    "FC26 R62(INTERNATIONAL)19.04.2026": {
      "total": 14,
      "finalizados": 14,
      "agendados": 0
    },
    "FC26 R63(PREMIER LEAGUE)20.04.2026": {
      "total": 20,
      "finalizados": 20,
      "agendados": 0
    },
    "FC26 R64(SERIA A)20.04.2026": {
      "total": 20,
      "finalizados": 20,
      "agendados": 0
    },
    "FC26 R65(COPA LIBERTADORES)20.04.2026": {
      "total": 20,
      "finalizados": 20,
      "agendados": 0
    },
    "FC26 R66(CHAMPIONS LEAGUE)20.04.2026": {
      "total": 20,
      "finalizados": 20,
      "agendados": 0
    },
    "FC26 R67(PREMIER LEAGUE)20.04.2026": {
      "total": 20,
      "finalizados": 20,
      "agendados": 0
    },
    "FC26 R68(CHAMPIONS LEAGUE)20.04.2026": {
      "total": 20,
      "finalizados": 20,
      "agendados": 0
    },
    "FC26 R69(INTERNATIONAL)20.04.2026": {
      "total": 20,
      "finalizados": 20,
      "agendados": 0
    },
    "FC26 R70(LA LIGA)20.04.2026": {
      "total": 20,
      "finalizados": 20,
      "agendados": 0
    },
    "FC26 R71(CHAMPIONS LEAGUE)20.04.2026": {
      "total": 20,
      "finalizados": 20,
      "agendados": 0
    },
    "FC26 R72(SERIA A)20.04.2026": {
      "total": 20,
      "finalizados": 20,
      "agendados": 0
    },
    "FC26 R73(INTERNATIONAL)20.04.2026": {
      "total": 20,
      "finalizados": 20,
      "agendados": 0
    },
    "FC26 R74(CHAMPIONS LEAGUE)20.04.2026": {
      "total": 20,
      "finalizados": 20,
      "agendados": 0
    },
    "FC26 R75(SERIA A)20.04.2026": {
      "total": 20,
      "finalizados": 18,
      "agendados": 2
    },
    "FC26 R76(LA LIGA)20.04.2026": {
      "total": 20,
      "finalizados": 16,
      "agendados": 4
    },
    "FC26 R77(CHAMPIONS LEAGUE)20.04.2026": {
      "total": 20,
      "finalizados": 0,
      "agendados": 20
    },
    "FC26 R78(PREMIER LEAGUE)20.04.2026": {
      "total": 20,
      "finalizados": 0,
      "agendados": 20
    },
    "FC26 R79(CHAMPIONS LEAGUE)20.04.2026": {
      "total": 8,
      "finalizados": 0,
      "agendados": 8
    },
    "FC26 R80(INTERNATIONAL)20.04.2026": {
      "total": 6,
      "finalizados": 0,
      "agendados": 6
    }
  },
  "classificacao": {
    "FC26 R61(CHAMPIONS LEAGUE)19.04.2026": [
      {
        "nome": "Barcelona (Eduardo)",
        "Pts": 10,
        "J": 4,
        "V": 3,
        "E": 1,
        "D": 0,
        "GP": 8,
        "GC": 3,
        "SG": 5,
        "pos": 1
      },
      {
        "nome": "Atletico Madrid (Odin)",
        "Pts": 9,
        "J": 5,
        "V": 3,
        "E": 0,
        "D": 2,
        "GP": 15,
        "GC": 7,
        "SG": 8,
        "pos": 2
      },
      {
        "nome": "Bayern M. (Dexter)",
        "Pts": 7,
        "J": 5,
        "V": 2,
        "E": 1,
        "D": 2,
        "GP": 12,
        "GC": 9,
        "SG": 3,
        "pos": 3
      },
      {
        "nome": "Real Madrid (Kai)",
        "Pts": 5,
        "J": 5,
        "V": 1,
        "E": 2,
        "D": 2,
        "GP": 12,
        "GC": 14,
        "SG": -2,
        "pos": 4
      },
      {
        "nome": "Liverpool (Conde)",
        "Pts": 3,
        "J": 5,
        "V": 1,
        "E": 0,
        "D": 4,
        "GP": 8,
        "GC": 22,
        "SG": -14,
        "pos": 5
      }
    ],
    "FC26 R62(INTERNATIONAL)19.04.2026": [
      {
        "nome": "Italy (Eric)",
        "Pts": 15,
        "J": 6,
        "V": 5,
        "E": 0,
        "D": 1,
        "GP": 25,
        "GC": 20,
        "SG": 5,
        "pos": 1
      },
      {
        "nome": "Morocco (Haidan)",
        "Pts": 10,
        "J": 6,
        "V": 3,
        "E": 1,
        "D": 2,
        "GP": 30,
        "GC": 26,
        "SG": 4,
        "pos": 2
      },
      {
        "nome": "Denmark (Felix)",
        "Pts": 5,
        "J": 5,
        "V": 1,
        "E": 2,
        "D": 2,
        "GP": 13,
        "GC": 13,
        "SG": 0,
        "pos": 3
      },
      {
        "nome": "France (George)",
        "Pts": 5,
        "J": 6,
        "V": 1,
        "E": 2,
        "D": 3,
        "GP": 14,
        "GC": 18,
        "SG": -4,
        "pos": 4
      },
      {
        "nome": "Ghana (Splinter)",
        "Pts": 4,
        "J": 5,
        "V": 1,
        "E": 1,
        "D": 3,
        "GP": 13,
        "GC": 18,
        "SG": -5,
        "pos": 5
      }
    ],
    "FC26 R63(PREMIER LEAGUE)20.04.2026": [
      {
        "nome": "Aston Villa (Eduardo)",
        "Pts": 16,
        "J": 8,
        "V": 5,
        "E": 1,
        "D": 2,
        "GP": 17,
        "GC": 12,
        "SG": 5,
        "pos": 1
      },
      {
        "nome": "West Ham United (Odin)",
        "Pts": 12,
        "J": 8,
        "V": 4,
        "E": 0,
        "D": 4,
        "GP": 28,
        "GC": 28,
        "SG": 0,
        "pos": 2
      },
      {
        "nome": "Manchester City (Dexter)",
        "Pts": 11,
        "J": 8,
        "V": 3,
        "E": 2,
        "D": 3,
        "GP": 22,
        "GC": 19,
        "SG": 3,
        "pos": 3
      },
      {
        "nome": "Arsenal (Conde)",
        "Pts": 11,
        "J": 8,
        "V": 3,
        "E": 2,
        "D": 3,
        "GP": 24,
        "GC": 25,
        "SG": -1,
        "pos": 4
      },
      {
        "nome": "Liverpool (Kai)",
        "Pts": 6,
        "J": 8,
        "V": 1,
        "E": 3,
        "D": 4,
        "GP": 19,
        "GC": 26,
        "SG": -7,
        "pos": 5
      }
    ],
    "FC26 R64(SERIA A)20.04.2026": [
      {
        "nome": "Juventus (Eric)",
        "Pts": 18,
        "J": 8,
        "V": 6,
        "E": 0,
        "D": 2,
        "GP": 41,
        "GC": 31,
        "SG": 10,
        "pos": 1
      },
      {
        "nome": "Milan (George)",
        "Pts": 11,
        "J": 8,
        "V": 3,
        "E": 2,
        "D": 3,
        "GP": 18,
        "GC": 15,
        "SG": 3,
        "pos": 2
      },
      {
        "nome": "Roma (Splinter)",
        "Pts": 11,
        "J": 8,
        "V": 3,
        "E": 2,
        "D": 3,
        "GP": 27,
        "GC": 27,
        "SG": 0,
        "pos": 3
      },
      {
        "nome": "Atalanta (Felix)",
        "Pts": 10,
        "J": 8,
        "V": 3,
        "E": 1,
        "D": 4,
        "GP": 30,
        "GC": 35,
        "SG": -5,
        "pos": 4
      },
      {
        "nome": "Fiorentina (Haidan)",
        "Pts": 6,
        "J": 8,
        "V": 1,
        "E": 3,
        "D": 4,
        "GP": 33,
        "GC": 41,
        "SG": -8,
        "pos": 5
      }
    ],
    "FC26 R65(COPA LIBERTADORES)20.04.2026": [
      {
        "nome": "Sao Paulo (Odin)",
        "Pts": 14,
        "J": 8,
        "V": 4,
        "E": 2,
        "D": 2,
        "GP": 29,
        "GC": 16,
        "SG": 13,
        "pos": 1
      },
      {
        "nome": "Penarol (Dexter)",
        "Pts": 13,
        "J": 8,
        "V": 4,
        "E": 1,
        "D": 3,
        "GP": 27,
        "GC": 25,
        "SG": 2,
        "pos": 2
      },
      {
        "nome": "San Lorenzo (Eduardo)",
        "Pts": 11,
        "J": 8,
        "V": 3,
        "E": 2,
        "D": 3,
        "GP": 19,
        "GC": 19,
        "SG": 0,
        "pos": 3
      },
      {
        "nome": "River Plate (Kai)",
        "Pts": 9,
        "J": 8,
        "V": 3,
        "E": 0,
        "D": 5,
        "GP": 17,
        "GC": 20,
        "SG": -3,
        "pos": 4
      },
      {
        "nome": "Bolivar (Conde)",
        "Pts": 9,
        "J": 8,
        "V": 2,
        "E": 3,
        "D": 3,
        "GP": 22,
        "GC": 34,
        "SG": -12,
        "pos": 5
      }
    ],
    "FC26 R66(CHAMPIONS LEAGUE)20.04.2026": [
      {
        "nome": "Bayern M. (George)",
        "Pts": 19,
        "J": 8,
        "V": 6,
        "E": 1,
        "D": 1,
        "GP": 26,
        "GC": 16,
        "SG": 10,
        "pos": 1
      },
      {
        "nome": "PSG (Felix)",
        "Pts": 11,
        "J": 8,
        "V": 3,
        "E": 2,
        "D": 3,
        "GP": 29,
        "GC": 23,
        "SG": 6,
        "pos": 2
      },
      {
        "nome": "Manchester City (Eric)",
        "Pts": 11,
        "J": 8,
        "V": 3,
        "E": 2,
        "D": 3,
        "GP": 30,
        "GC": 28,
        "SG": 2,
        "pos": 3
      },
      {
        "nome": "Borussia Dortmund (Splinter)",
        "Pts": 9,
        "J": 8,
        "V": 2,
        "E": 3,
        "D": 3,
        "GP": 21,
        "GC": 23,
        "SG": -2,
        "pos": 4
      },
      {
        "nome": "Bayer Leverkusen (Haidan)",
        "Pts": 6,
        "J": 8,
        "V": 2,
        "E": 0,
        "D": 6,
        "GP": 24,
        "GC": 40,
        "SG": -16,
        "pos": 5
      }
    ],
    "FC26 R67(PREMIER LEAGUE)20.04.2026": [
      {
        "nome": "Aston Villa (Alexis)",
        "Pts": 19,
        "J": 8,
        "V": 6,
        "E": 1,
        "D": 1,
        "GP": 31,
        "GC": 18,
        "SG": 13,
        "pos": 1
      },
      {
        "nome": "Tottenham (Flash)",
        "Pts": 15,
        "J": 8,
        "V": 5,
        "E": 0,
        "D": 3,
        "GP": 29,
        "GC": 30,
        "SG": -1,
        "pos": 2
      },
      {
        "nome": "Chelsea (Gabriel)",
        "Pts": 11,
        "J": 8,
        "V": 3,
        "E": 2,
        "D": 3,
        "GP": 26,
        "GC": 22,
        "SG": 4,
        "pos": 3
      },
      {
        "nome": "Manchester City (Cleo)",
        "Pts": 7,
        "J": 8,
        "V": 2,
        "E": 1,
        "D": 5,
        "GP": 22,
        "GC": 27,
        "SG": -5,
        "pos": 4
      },
      {
        "nome": "Arsenal (Leonardo)",
        "Pts": 6,
        "J": 8,
        "V": 2,
        "E": 0,
        "D": 6,
        "GP": 24,
        "GC": 35,
        "SG": -11,
        "pos": 5
      }
    ],
    "FC26 R68(CHAMPIONS LEAGUE)20.04.2026": [
      {
        "nome": "Atletico Madrid (Andrew)",
        "Pts": 18,
        "J": 8,
        "V": 6,
        "E": 0,
        "D": 2,
        "GP": 30,
        "GC": 23,
        "SG": 7,
        "pos": 1
      },
      {
        "nome": "Liverpool (Luigi)",
        "Pts": 16,
        "J": 8,
        "V": 5,
        "E": 1,
        "D": 2,
        "GP": 33,
        "GC": 25,
        "SG": 8,
        "pos": 2
      },
      {
        "nome": "Barcelona (Mateo)",
        "Pts": 11,
        "J": 8,
        "V": 3,
        "E": 2,
        "D": 3,
        "GP": 33,
        "GC": 30,
        "SG": 3,
        "pos": 3
      },
      {
        "nome": "Real Madrid (VanGogh)",
        "Pts": 10,
        "J": 8,
        "V": 3,
        "E": 1,
        "D": 4,
        "GP": 26,
        "GC": 25,
        "SG": 1,
        "pos": 4
      },
      {
        "nome": "Manchester City (MisterX)",
        "Pts": 3,
        "J": 8,
        "V": 1,
        "E": 0,
        "D": 7,
        "GP": 23,
        "GC": 42,
        "SG": -19,
        "pos": 5
      }
    ],
    "FC26 R69(INTERNATIONAL)20.04.2026": [
      {
        "nome": "Norway (Alexis)",
        "Pts": 16,
        "J": 8,
        "V": 5,
        "E": 1,
        "D": 2,
        "GP": 34,
        "GC": 26,
        "SG": 8,
        "pos": 1
      },
      {
        "nome": "Argentina (Flash)",
        "Pts": 15,
        "J": 8,
        "V": 5,
        "E": 0,
        "D": 3,
        "GP": 28,
        "GC": 25,
        "SG": 3,
        "pos": 2
      },
      {
        "nome": "Denmark (Gabriel)",
        "Pts": 10,
        "J": 8,
        "V": 3,
        "E": 1,
        "D": 4,
        "GP": 25,
        "GC": 26,
        "SG": -1,
        "pos": 3
      },
      {
        "nome": "France (Cleo)",
        "Pts": 9,
        "J": 8,
        "V": 3,
        "E": 0,
        "D": 5,
        "GP": 27,
        "GC": 31,
        "SG": -4,
        "pos": 4
      },
      {
        "nome": "Holland (Leonardo)",
        "Pts": 9,
        "J": 8,
        "V": 3,
        "E": 0,
        "D": 5,
        "GP": 31,
        "GC": 37,
        "SG": -6,
        "pos": 5
      }
    ],
    "FC26 R70(LA LIGA)20.04.2026": [
      {
        "nome": "Barcelona (VanGogh)",
        "Pts": 15,
        "J": 8,
        "V": 5,
        "E": 0,
        "D": 3,
        "GP": 28,
        "GC": 21,
        "SG": 7,
        "pos": 1
      },
      {
        "nome": "Real Madrid (Luigi)",
        "Pts": 13,
        "J": 8,
        "V": 4,
        "E": 1,
        "D": 3,
        "GP": 33,
        "GC": 27,
        "SG": 6,
        "pos": 2
      },
      {
        "nome": "Real Betis (Andrew)",
        "Pts": 12,
        "J": 8,
        "V": 4,
        "E": 0,
        "D": 4,
        "GP": 24,
        "GC": 26,
        "SG": -2,
        "pos": 3
      },
      {
        "nome": "Sevilla (MisterX)",
        "Pts": 10,
        "J": 8,
        "V": 3,
        "E": 1,
        "D": 4,
        "GP": 24,
        "GC": 30,
        "SG": -6,
        "pos": 4
      },
      {
        "nome": "Atletic Bilbao (Mateo)",
        "Pts": 8,
        "J": 8,
        "V": 2,
        "E": 2,
        "D": 4,
        "GP": 26,
        "GC": 31,
        "SG": -5,
        "pos": 5
      }
    ],
    "FC26 R71(CHAMPIONS LEAGUE)20.04.2026": [
      {
        "nome": "Barcelona (Alexis)",
        "Pts": 16,
        "J": 8,
        "V": 5,
        "E": 1,
        "D": 2,
        "GP": 35,
        "GC": 22,
        "SG": 13,
        "pos": 1
      },
      {
        "nome": "Atletico Madrid (Gabriel)",
        "Pts": 16,
        "J": 8,
        "V": 5,
        "E": 1,
        "D": 2,
        "GP": 33,
        "GC": 28,
        "SG": 5,
        "pos": 2
      },
      {
        "nome": "PSG (Flash)",
        "Pts": 11,
        "J": 8,
        "V": 3,
        "E": 2,
        "D": 3,
        "GP": 28,
        "GC": 28,
        "SG": 0,
        "pos": 3
      },
      {
        "nome": "Bayern M. (Leonardo)",
        "Pts": 8,
        "J": 8,
        "V": 2,
        "E": 2,
        "D": 4,
        "GP": 27,
        "GC": 31,
        "SG": -4,
        "pos": 4
      },
      {
        "nome": "Real Madrid (Cleo)",
        "Pts": 5,
        "J": 8,
        "V": 1,
        "E": 2,
        "D": 5,
        "GP": 14,
        "GC": 28,
        "SG": -14,
        "pos": 5
      }
    ],
    "FC26 R72(SERIA A)20.04.2026": [
      {
        "nome": "Napoli (Andrew)",
        "Pts": 20,
        "J": 8,
        "V": 6,
        "E": 2,
        "D": 0,
        "GP": 31,
        "GC": 20,
        "SG": 11,
        "pos": 1
      },
      {
        "nome": "Lazio (Mateo)",
        "Pts": 13,
        "J": 8,
        "V": 4,
        "E": 1,
        "D": 3,
        "GP": 27,
        "GC": 24,
        "SG": 3,
        "pos": 2
      },
      {
        "nome": "Milan (VanGogh)",
        "Pts": 11,
        "J": 8,
        "V": 3,
        "E": 2,
        "D": 3,
        "GP": 25,
        "GC": 25,
        "SG": 0,
        "pos": 3
      },
      {
        "nome": "Inter (Luigi)",
        "Pts": 7,
        "J": 8,
        "V": 2,
        "E": 1,
        "D": 5,
        "GP": 30,
        "GC": 31,
        "SG": -1,
        "pos": 4
      },
      {
        "nome": "Juventus (MisterX)",
        "Pts": 6,
        "J": 8,
        "V": 2,
        "E": 0,
        "D": 6,
        "GP": 30,
        "GC": 43,
        "SG": -13,
        "pos": 5
      }
    ],
    "FC26 R73(INTERNATIONAL)20.04.2026": [
      {
        "nome": "Argentina (Donatello)",
        "Pts": 14,
        "J": 8,
        "V": 4,
        "E": 2,
        "D": 2,
        "GP": 28,
        "GC": 24,
        "SG": 4,
        "pos": 1
      },
      {
        "nome": "Portugal (Oliver)",
        "Pts": 14,
        "J": 8,
        "V": 3,
        "E": 5,
        "D": 0,
        "GP": 24,
        "GC": 20,
        "SG": 4,
        "pos": 2
      },
      {
        "nome": "Holland (Liam)",
        "Pts": 11,
        "J": 8,
        "V": 3,
        "E": 2,
        "D": 3,
        "GP": 26,
        "GC": 28,
        "SG": -2,
        "pos": 3
      },
      {
        "nome": "Denmark (Noah)",
        "Pts": 10,
        "J": 8,
        "V": 3,
        "E": 1,
        "D": 4,
        "GP": 30,
        "GC": 28,
        "SG": 2,
        "pos": 4
      },
      {
        "nome": "France (Logan)",
        "Pts": 5,
        "J": 8,
        "V": 1,
        "E": 2,
        "D": 5,
        "GP": 20,
        "GC": 28,
        "SG": -8,
        "pos": 5
      }
    ],
    "FC26 R74(CHAMPIONS LEAGUE)20.04.2026": [
      {
        "nome": "PSG (Beckham)",
        "Pts": 18,
        "J": 8,
        "V": 6,
        "E": 0,
        "D": 2,
        "GP": 38,
        "GC": 28,
        "SG": 10,
        "pos": 1
      },
      {
        "nome": "Barcelona (Kai)",
        "Pts": 15,
        "J": 8,
        "V": 4,
        "E": 3,
        "D": 1,
        "GP": 21,
        "GC": 12,
        "SG": 9,
        "pos": 2
      },
      {
        "nome": "Atletico Madrid (Dominic)",
        "Pts": 10,
        "J": 8,
        "V": 2,
        "E": 4,
        "D": 2,
        "GP": 27,
        "GC": 26,
        "SG": 1,
        "pos": 3
      },
      {
        "nome": "Real Madrid (George)",
        "Pts": 6,
        "J": 8,
        "V": 1,
        "E": 3,
        "D": 4,
        "GP": 18,
        "GC": 23,
        "SG": -5,
        "pos": 4
      },
      {
        "nome": "Bayern M. (Juan)",
        "Pts": 5,
        "J": 8,
        "V": 1,
        "E": 2,
        "D": 5,
        "GP": 16,
        "GC": 31,
        "SG": -15,
        "pos": 5
      }
    ],
    "FC26 R75(SERIA A)20.04.2026": [
      {
        "nome": "Milan (Logan)",
        "Pts": 14,
        "J": 7,
        "V": 4,
        "E": 2,
        "D": 1,
        "GP": 21,
        "GC": 15,
        "SG": 6,
        "pos": 1
      },
      {
        "nome": "Atalanta (Noah)",
        "Pts": 14,
        "J": 8,
        "V": 4,
        "E": 2,
        "D": 2,
        "GP": 29,
        "GC": 24,
        "SG": 5,
        "pos": 2
      },
      {
        "nome": "Napoli (Oliver)",
        "Pts": 13,
        "J": 7,
        "V": 4,
        "E": 1,
        "D": 2,
        "GP": 26,
        "GC": 21,
        "SG": 5,
        "pos": 3
      },
      {
        "nome": "Lazio (Donatello)",
        "Pts": 7,
        "J": 7,
        "V": 2,
        "E": 1,
        "D": 4,
        "GP": 13,
        "GC": 19,
        "SG": -6,
        "pos": 4
      },
      {
        "nome": "Inter (Liam)",
        "Pts": 3,
        "J": 7,
        "V": 1,
        "E": 0,
        "D": 6,
        "GP": 16,
        "GC": 26,
        "SG": -10,
        "pos": 5
      }
    ],
    "FC26 R76(LA LIGA)20.04.2026": [
      {
        "nome": "Real Betis (Dominic)",
        "Pts": 18,
        "J": 7,
        "V": 6,
        "E": 0,
        "D": 1,
        "GP": 32,
        "GC": 16,
        "SG": 16,
        "pos": 1
      },
      {
        "nome": "Real Madrid (Juan)",
        "Pts": 12,
        "J": 7,
        "V": 4,
        "E": 0,
        "D": 3,
        "GP": 17,
        "GC": 20,
        "SG": -3,
        "pos": 2
      },
      {
        "nome": "Barcelona (George)",
        "Pts": 9,
        "J": 6,
        "V": 3,
        "E": 0,
        "D": 3,
        "GP": 13,
        "GC": 13,
        "SG": 0,
        "pos": 3
      },
      {
        "nome": "Athletic Bilbao (Kai)",
        "Pts": 4,
        "J": 6,
        "V": 1,
        "E": 1,
        "D": 4,
        "GP": 14,
        "GC": 20,
        "SG": -6,
        "pos": 4
      },
      {
        "nome": "Real Sociedad (Beckham)",
        "Pts": 4,
        "J": 6,
        "V": 1,
        "E": 1,
        "D": 4,
        "GP": 18,
        "GC": 25,
        "SG": -7,
        "pos": 5
      }
    ]
  }
}